Workbook

Sheet 总览
A1: Steam 视觉小说 2020–2025｜扩展总览 | R1: 分类 | S1: 游戏数 | U1: 年份 | V1: 全部游戏
R2: 全年龄 | S2: =COUNTIF(游戏总表!$R$2:$R$4661,AF2) -> 0 | U2: =年度统计!A2 -> 2020 | V2: =年度统计!B2 -> 498
A3: 原始交集名单 + 仅由 VNDB 补充的完整游戏；评论热度与成人内容分类规则详见“参数与口径” | R3: 非全年龄 | S3: =COUNTIF(游戏总表!$R$2:$R$4661,AF3) -> 0 | U3: =年度统计!A3 -> 2021 | V3: =年度统计!B3 -> 590
R4: 未知 | S4: =COUNTIF(游戏总表!$R$2:$R$4661,AF4) -> 0 | U4: =年度统计!A4 -> 2022 | V4: =年度统计!B4 -> 758
A5: 纳入统计的游戏总数 | F5: 新增：仅由 VNDB 补充的完整游戏 | K5: 已取得估算销量的游戏 | U5: =年度统计!A5 -> 2023 | V5: =年度统计!B5 -> 814
A6: =COUNTA(游戏总表!$A$2:$A$4661) -> 4660 | F6: =COUNTIF(游戏总表!$Z$2:$Z$4661,"VNDB_ONLY_COMPLETE_INCREMENT") -> 1820 | K6: =COUNT(游戏总表!$I$2:$I$4661) -> 4259 | U6: =年度统计!A6 -> 2024 | V6: =年度统计!B6 -> 992
U7: =年度统计!A7 -> 2025 | V7: =年度统计!B7 -> 1008
A11: 高热度游戏（Steam 评论数>198） | F11: 全年龄游戏（无色情内容标记） | K11: 非全年龄游戏（含色情内容标记）
A12: =COUNTIF(游戏总表!$K$2:$K$4661,">198") -> 934 | F12: =COUNTIF(游戏总表!$R$2:$R$4661,"全年龄") -> 3336 | K12: =COUNTIF(游戏总表!$R$2:$R$4661,"非全年龄") -> 1324

Sheet 参数与口径
A1: 参数、分类规则与数据来源
A4: 参数 | B4: 数值 / 说明
A5: 评论热度阈值 | B5: 198
A6: 阈值以下实际占比 | B6: 0.79957082
A7: 统计截止日 | B7: 46242
A8: 新增名单选择 | B8: 只纳入原名单之外、仅由 VNDB 找到且发行类型为“完整游戏”的记录（技术值：VNDB_ONLY；vndb_rtypes=complete）
A9: 全年龄游戏 | B9: 所有关联发行版本中都没有色情内容标记，并且至少一个版本明确标记为不含色情内容（技术字段：has_ero=false）
A10: 非全年龄游戏 | B10: 任一关联发行版本明确标记为包含色情内容（技术字段：has_ero=true）
A11: 年龄分级（minage） | B11: 只记录年龄门槛，例如 18+；它不能单独证明游戏包含色情内容
A12: 估算累计销量（copiesSold） | B12: Gamalytic 对截至采集日累计售出份数的估算，不是官方销量，也不是发行当月销量
A13: 上市时长 | B13: 从发行日到 2026-08-08 的月数
A15: 数据源 | B15: URL
A16: VNDB Release API | B16: https://api.vndb.org/kana
A17: Steam 官方评论接口说明 | B17: https://partner.steamgames.com/doc/store/getreviews
A18: Gamalytic API | B18: https://api.gamalytic.com/reference/
A20: 英文字段名 | B20: 中文名称 | C20: 给非技术人员的解释 | D20: 数据来源 / 注意事项
A21: steam_appid | B21: Steam 应用编号 | C21: Steam 为每个商店应用分配的唯一数字编号，用于准确识别游戏。 | D21: Steam；同名游戏也可以用该编号区分。
A22: name | B22: 游戏名称 | C22: Steam 商店中显示的游戏名称。 | D22: Steam 商店。
A23: steam_release_date | B23: Steam 发行日期 | C23: 游戏在 Steam 上正式发行的日期。 | D23: Steam；格式为年-月-日。
A24: release_month | B24: 发行月份 | C24: 把发行日期整理到月份，便于统计每月发行数量。 | D24: 根据 Steam 发行日期计算；格式为年-月。
A25: release_year | B25: 发行年份 | C25: 把发行日期整理到年份，便于进行年度比较。 | D25: 根据 Steam 发行日期计算。
A26: months_since_release | B26: 上市时长（月） | C26: 从 Steam 发行日到统计截止日经历的月数。 | D26: 计算值；截止日为 2026-08-08。
A27: store_url | B27: Steam 商店链接 | C27: 打开该游戏 Steam 商店页面的网址。 | D27: Steam。
A28: vndb_url | B28: VNDB 作品链接 | C28: 打开该游戏对应 VNDB 视觉小说条目的网址。 | D28: VNDB；一个 Steam 游戏可能关联多个 VNDB 记录，此处提供主要链接。
A29: copies_sold | B29: 估算累计销量 | C29: Gamalytic 估算该游戏截至采集日累计售出的份数。 | D29: Gamalytic 估算值，不是 Steam 官方销量；缺失时留空。
A30: gamalytic_status | B30: 销量取数状态 | C30: 说明是否成功从 Gamalytic 获得估算销量。 | D30: FOUND=已取得；NOT_FOUND 等值表示未取得。
A31: steam_review_count | B31: Steam 评论总数 | C31: Steam 商店中该游戏收到的用户评论总数。 | D31: Steam 官方评论接口；包含所选语言范围内的评论。
... A54: copies_sold_fetched_at | B54: 销量估算采集时间 | C54: 取得 Gamalytic 估算销量的时间。 | D54: 通常为带时区的时间戳；便于日后更新和核对。

Sheet 游戏总表
A1: steam_appid | B1: name | C1: steam_release_date | D1: release_month | E1: release_year | F1: months_since_release | G1: store_url | H1: vndb_url | I1: copies_sold | J1: gamalytic_status | K1: steam_review_count | L1: steam_review_positive | M1: steam_review_negative | N1: steam_review_positive_rate | O1: steam_review_score_desc | P1: steam_review_status | Q1: review_heat_group | R1: all_ages_status | S1: is_all_ages | T1: has_ero_any | U1: sexual_content_basis | V1: vndb_minage_values | W1: vndb_has_ero_values | X1: vndb_uncensored_values | Y1: sexual_content_conflict | Z1: expanded_source | AA1: in_steam_visual_novel_tag | AB1: vndb_ids | AC1: vndb_release_ids | AD1: vndb_rtypes | AE1: vndb_official | AF1: price_text | AG1: is_free | AH1: copies_sold_fetched_at
A2: 1205160 | B2: Decadent Thinking | C2: 43831 | D2: 2020-01 | E2: 2020 | F2: 79.21 | G2: https://store.steampowered.com/app/1205160/ | H2: https://vndb.org/v27532 | I2: 277 | J2: FOUND | K2: 12 | L2: 9 | M2: 3 | N2: 0.75 | O2: Mostly Positive | P2: FOUND | Q2: 低热度（≤198） | R2: 全年龄 | S2: TRUE | T2: FALSE | U2: has_ero=false | W2: FALSE | Y2: FALSE | Z2: ORIGINAL_INTERSECTION | AA2: TRUE | AB2: v27532 | AC2: r79683 | AD2: complete | AE2: TRUE | AF2: $14.99 | AG2: FALSE | AH2: 46242.565
A3: 1168470 | B3: 千面 Melancholy Love | C3: 43832 | D3: 2020-01 | E3: 2020 | F3: 79.18 | G3: https://store.steampowered.com/app/1168470/ | H3: https://vndb.org/v27565 | I3: 26569 | J3: FOUND | K3: 2234 | L3: 2114 | M3: 120 | N3: 0.94628469 | O3: Very Positive | P3: FOUND | Q3: 高热度（>198） | R3: 全年龄 | S3: TRUE | T3: FALSE | U3: has_ero=false | W3: FALSE | Y3: FALSE | Z3: ORIGINAL_INTERSECTION | AA3: TRUE | AB3: v27565 | AC3: r68714 | AD3: complete | AE3: TRUE | AF3: $4.99 | AG3: FALSE | AH3: 46242.565
A4: 1049100 | B4: 泡沫冬景 | C4: 43832 | D4: 2020-01 | E4: 2020 | F4: 79.18 | G4: https://store.steampowered.com/app/1049100/ | H4: https://vndb.org/v24208 | I4: 90198 | J4: FOUND | K4: 4505 | L4: 4297 | M4: 208 | N4: 0.95382908 | O4: Overwhelmingly Positive | P4: FOUND | Q4: 高热度（>198） | R4: 全年龄 | S4: TRUE | T4: FALSE | U4: has_ero=false | W4: FALSE | Y4: FALSE | Z4: ORIGINAL_INTERSECTION | AA4: TRUE | AB4: v24208 | AC4: r81838 | AD4: complete | AE4: TRUE | AF4: $14.99 | AG4: FALSE | AH4: 46242.565
A5: 590800 | B5: Rainbow Dreams | C5: 43833 | D5: 2020-01 | E5: 2020 | F5: 79.15 | G5: https://store.steampowered.com/app/590800/ | H5: https://vndb.org/v20128 | I5: 118 | J5: FOUND | K5: 7 | L5: 5 | M5: 2 | N5: 0.71428571 | O5: 7 user reviews | P5: FOUND | Q5: 低热度（≤198） | R5: 全年龄 | S5: TRUE | T5: FALSE | U5: has_ero=false | W5: FALSE | Y5: FALSE | Z5: ORIGINAL_INTERSECTION | AA5: TRUE | AB5: v20128 | AC5: r51184 | AD5: complete | AE5: TRUE | AF5: $9.99 | AG5: FALSE | AH5: 46242.565
A6: 1130900 | B6: 黎明霞光 | C6: 43840 | D6: 2020-01 | E6: 2020 | F6: 78.92 | G6: https://store.steampowered.com/app/1130900/ | H6: https://vndb.org/v27663 | I6: 140 | J6: FOUND | K6: 11 | L6: 7 | M6: 4 | N6: 0.63636364 | O6: Mixed | P6: FOUND | Q6: 低热度（≤198） | R6: 全年龄 | S6: TRUE | T6: FALSE | U6: has_ero=false | W6: FALSE | Y6: FALSE | Z6: ORIGINAL_INTERSECTION | AA6: TRUE | AB6: v27663 | AC6: r68896 | AD6: complete | AE6: TRUE | AF6: $2.99 | AG6: FALSE | AH6: 46242.565
A7: 1216080 | B7: 坦率的小红帽和爱说谎的狼 | C7: 43843 | D7: 2020-01 | E7: 2020 | F7: 78.82 | G7: https://store.steampowered.com/app/1216080/ | H7: https://vndb.org/v26215 | I7: 76478 | J7: FOUND | K7: 1132 | L7: 1112 | M7: 20 | N7: 0.98233216 | O7: Overwhelmingly Positive | P7: FOUND | Q7: 高热度（>198） | R7: 全年龄 | S7: TRUE | T7: FALSE | U7: has_ero=false | W7: FALSE | Y7: FALSE | Z7: ORIGINAL_INTERSECTION | AA7: TRUE | AB7: v26215 | AC7: r68929 | AD7: complete | AE7: TRUE | AF7: Free | AG7: TRUE | AH7: 46242.565
A8: 1071350 | B8: Little One - A Visual Novel | C8: 43844 | D8: 2020-01 | E8: 2020 | F8: 78.78 | G8: https://store.steampowered.com/app/1071350/ | H8: https://vndb.org/v24659 | I8: 952 | J8: FOUND | K8: 28 | L8: 21 | M8: 7 | N8: 0.75 | O8: Mostly Positive | P8: FOUND | Q8: 低热度（≤198） | R8: 全年龄 | S8: TRUE | T8: FALSE | U8: has_ero=false | W8: FALSE | Y8: FALSE | Z8: ORIGINAL_INTERSECTION | AA8: TRUE | AB8: v24659 | AC8: r68937 | AD8: complete | AE8: TRUE | AF8: $9.99 | AG8: FALSE | AH8: 46242.565
A9: 1217390 | B9: Some Some Convenience Store | C9: 43844 | D9: 2020-01 | E9: 2020 | F9: 78.78 | G9: https://store.steampowered.com/app/1217390/ | H9: https://vndb.org/v27704 | I9: 70930 | J9: FOUND | K9: 3101 | L9: 2975 | M9: 126 | N9: 0.95936795 | O9: Overwhelmingly Positive | P9: FOUND | Q9: 高热度（>198） | R9: 全年龄 | S9: TRUE | T9: FALSE | U9: VNDB minage=15; has_ero=false | V9: 15 | W9: FALSE | Y9: FALSE | Z9: ORIGINAL_INTERSECTION | AA9: TRUE | AB9: v27704 | AC9: r122970 | AD9: complete | AE9: TRUE | AF9: $14.99 | AG9: FALSE | AH9: 46242.565
A10: 1179100 | B10: Oppaidius Tropical Cruise! | C10: 43846 | D10: 2020-01 | E10: 2020 | F10: 78.72 | G10: https://store.steampowered.com/app/1179100/ | H10: https://vndb.org/v26772 | I10: 11169 | J10: FOUND | K10: 146 | L10: 133 | M10: 13 | N10: 0.9109589 | O10: Very Positive | P10: FOUND | Q10: 低热度（≤198） | R10: 全年龄 | S10: TRUE | T10: FALSE | U10: has_ero=false | W10: FALSE | Y10: FALSE | Z10: VNDB_ONLY_COMPLETE_INCREMENT | AA10: FALSE | AB10: v26772 | AC10: r66996 | AD10: complete | AE10: TRUE | AG10: FALSE | AH10: 46242.565
A11: 1148930 | B11: Chuusotsu! 1.5th Graduation: The Moving Castle | C11: 43847 | D11: 2020-01 | E11: 2020 | F11: 78.69 | G11: https://store.steampowered.com/app/1148930/ | H11: https://vndb.org/v21410 | I11: 368 | J11: FOUND | K11: 23 | L11: 22 | M11: 1 | N11: 0.95652174 | O11: Positive | P11: FOUND | Q11: 低热度（≤198） | R11: 全年龄 | S11: TRUE | T11: FALSE | U11: has_ero=false | W11: FALSE | Y11: FALSE | Z11: ORIGINAL_INTERSECTION | AA11: TRUE | AB11: v21410 | AC11: r52277 | AD11: complete | AE11: TRUE | AF11: $9.99 | AG11: FALSE | AH11: 46242.565
A12: 1198630 | B12: Customer Cums First! | C12: 43847 | D12: 2020-01 | E12: 2020 | F12: 78.69 | G12: https://store.steampowered.com/app/1198630/ | H12: https://vndb.org/v13956 | I12: 1340 | J12: FOUND | K12: 34 | L12: 23 | M12: 11 | N12: 0.67647059 | O12: Mixed | P12: FOUND | Q12: 低热度（≤198） | R12: 非全年龄 | S12: FALSE | T12: TRUE | U12: VNDB minage=18; has_ero=true; uncensored=false | V12: 18 | W12: TRUE | X12: FALSE | Y12: FALSE | Z12: VNDB_ONLY_COMPLETE_INCREMENT | AA12: FALSE | AB12: v13956 | AC12: r68719;r86147 | AD12: complete | AE12: TRUE | AG12: FALSE | AH12: 46242.565
A13: 1215120 | B13: DeeperRed2028-WeAreEscape- | C13: 43847 | D13: 2020-01 | E13: 2020 | F13: 78.69 | G13: https://store.steampowered.com/app/1215120/ | H13: https://vndb.org/v27703 | I13: 140 | J13: FOUND | K13: 10 | L13: 10 | M13: 0 | N13: 1 | O13: Positive | P13: FOUND | Q13: 低热度（≤198） | R13: 全年龄 | S13: TRUE | T13: FALSE | U13: has_ero=false | W13: FALSE | Y13: FALSE | Z13: ORIGINAL_INTERSECTION | AA13: TRUE | AB13: v27703 | AC13: r68990 | AD13: complete | AE13: TRUE | AF13: $1.99 | AG13: FALSE | AH13: 46242.565
A14: 1215680 | B14: LVN Fake News - Adult Patch | C14: 43847 | D14: 2020-01 | E14: 2020 | F14: 78.69 | G14: https://store.steampowered.com/app/1215680/ | H14: https://vndb.org/v24006 | J14: NOT_FOUND | K14: 1 | L14: 1 | M14: 0 | N14: 1 | O14: 1 user reviews | P14: FOUND | Q14: 低热度（≤198） | R14: 非全年龄 | S14: FALSE | T14: TRUE | U14: VNDB minage=18; has_ero=true; uncensored=false | V14: 18 | W14: TRUE | X14: FALSE | Y14: FALSE | Z14: VNDB_ONLY_COMPLETE_INCREMENT | AA14: FALSE | AB14: v24006 | AC14: r68988 | AD14: complete | AE14: TRUE | AG14: FALSE | AH14: 46242.565
A15: 1118000 | B15: Revenant March | C15: 43847 | D15: 2020-01 | E15: 2020 | F15: 78.69 | G15: https://store.steampowered.com/app/1118000/ | H15: https://vndb.org/v27702 | I15: 518 | J15: FOUND | K15: 22 | L15: 20 | M15: 2 | N15: 0.90909091 | O15: Positive | P15: FOUND | Q15: 低热度（≤198） | R15: 全年龄 | S15: TRUE | T15: FALSE | U15: has_ero=false | W15: FALSE | Y15: FALSE | Z15: ORIGINAL_INTERSECTION | AA15: TRUE | AB15: v27702 | AC15: r68989 | AD15: complete | AE15: TRUE | AF15: $4.99 | AG15: FALSE | AH15: 46242.565
A16: 1017880 | B16: The Dark Side | C16: 43850 | D16: 2020-01 | E16: 2020 | F16: 78.59 | G16: https://store.steampowered.com/app/1017880/ | H16: https://vndb.org/v27644 | I16: 286 | J16: FOUND | K16: 13 | L16: 8 | M16: 5 | N16: 0.61538462 | O16: Mixed | P16: FOUND | Q16: 低热度（≤198） | R16: 全年龄 | S16: TRUE | T16: FALSE | U16: VNDB minage=10; has_ero=false | V16: 10 | W16: FALSE | Y16: FALSE | Z16: ORIGINAL_INTERSECTION | AA16: TRUE | AB16: v27644 | AC16: r68834 | AD16: complete | AE16: TRUE | AF16: $0.99 | AG16: FALSE | AH16: 46242.565
A17: 1193330 | B17: Together - A Wish No One Remembers | C17: 43850 | D17: 2020-01 | E17: 2020 | F17: 78.59 | G17: https://store.steampowered.com/app/1193330/ | H17: https://vndb.org/v27735 | I17: 165 | J17: FOUND | K17: 11 | L17: 11 | M17: 0 | N17: 1 | O17: Positive | P17: FOUND | Q17: 低热度（≤198） | R17: 全年龄 | S17: TRUE | T17: FALSE | U17: VNDB minage=0; has_ero=false | V17: 0 | W17: FALSE | Y17: FALSE | Z17: ORIGINAL_INTERSECTION | AA17: TRUE | AB17: v27735 | AC17: r69056;r74329 | AD17: complete;trial | AE17: TRUE | AF17: $1.99 | AG17: FALSE | AH17: 46242.565
A18: 1149550 | B18: Utawarerumono: Mask of Deception | C18: 43853 | D18: 2020-01 | E18: 2020 | F18: 78.49 | G18: https://store.steampowered.com/app/1149550/ | H18: https://vndb.org/v7721 | I18: 52299 | J18: FOUND | K18: 1377 | L18: 1276 | M18: 101 | N18: 0.92665214 | O18: Very Positive | P18: FOUND | Q18: 高热度（>198） | R18: 全年龄 | S18: TRUE | T18: FALSE | U18: has_ero=false | W18: FALSE | Y18: FALSE | Z18: ORIGINAL_INTERSECTION | AA18: TRUE | AB18: v7721 | AC18: r68816 | AD18: complete | AE18: TRUE | AF18: $39.99 | AG18: FALSE | AH18: 46242.565
A19: 1151440 | B19: Utawarerumono: Mask of Truth | C19: 43853 | D19: 2020-01 | E19: 2020 | F19: 78.49 | G19: https://store.steampowered.com/app/1151440/ | H19: https://vndb.org/v18717 | I19: 35712 | J19: FOUND | K19: 1508 | L19: 1453 | M19: 55 | N19: 0.96352785 | O19: Overwhelmingly Positive | P19: FOUND | Q19: 高热度（>198） | R19: 全年龄 | S19: TRUE | T19: FALSE | U19: has_ero=false | W19: FALSE | Y19: FALSE | Z19: ORIGINAL_INTERSECTION | AA19: TRUE | AB19: v18717 | AC19: r68817 | AD19: complete | AE19: TRUE | AF19: $39.99 | AG19: FALSE | AH19: 46242.565
A20: 1123190 | B20: 育种村 | C20: 43854 | D20: 2020-01 | E20: 2020 | F20: 78.46 | G20: https://store.steampowered.com/app/1123190/ | H20: https://vndb.org/v23154 | I20: 3905 | J20: FOUND | K20: 87 | L20: 62 | M20: 25 | N20: 0.71264368 | O20: Mostly Positive | P20: FOUND | Q20: 低热度（≤198） | R20: 非全年龄 | S20: FALSE | T20: TRUE | U20: VNDB minage=18; has_ero=true; uncensored=false | V20: 18 | W20: TRUE | X20: FALSE | Y20: FALSE | Z20: VNDB_ONLY_COMPLETE_INCREMENT | AA20: FALSE | AB20: v23154 | AC20: r69113 | AD20: complete | AE20: TRUE | AG20: FALSE | AH20: 46242.565
A21: 1180360 | B21: Two Love | C21: 43855 | D21: 2020-01 | E21: 2020 | F21: 78.42 | G21: https://store.steampowered.com/app/1180360/ | H21: https://vndb.org/v27760 | I21: 396 | J21: FOUND | K21: 11 | L21: 10 | M21: 1 | N21: 0.90909091 | O21: Positive | P21: FOUND | Q21: 低热度（≤198） | R21: 全年龄 | S21: TRUE | T21: FALSE | U21: has_ero=false | W21: FALSE | Y21: FALSE | Z21: ORIGINAL_INTERSECTION | AA21: TRUE | AB21: v27760 | AC21: r69123 | AD21: complete | AE21: TRUE | AF21: Free | AG21: TRUE | AH21: 46242.565
A22: 1165920 | B22: Lives so Sweet | C22: 43856 | D22: 2020-01 | E22: 2020 | F22: 78.39 | G22: https://store.steampowered.com/app/1165920/ | H22: https://vndb.org/v26393 | I22: 662 | J22: FOUND | K22: 20 | L22: 14 | M22: 6 | N22: 0.7 | O22: Mostly Positive | P22: FOUND | Q22: 低热度（≤198） | R22: 非全年龄 | S22: FALSE | T22: TRUE | U22: VNDB minage=18; has_ero=true; uncensored=true | V22: 18 | W22: TRUE | X22: TRUE | Y22: FALSE | Z22: VNDB_ONLY_COMPLETE_INCREMENT | AA22: FALSE | AB22: v26393 | AC22: r65652 | AD22: complete | AE22: TRUE | AG22: FALSE | AH22: 46242.565
A23: 914800 | B23: Coffee Talk | C23: 43859 | D23: 2020-01 | E23: 2020 | F23: 78.29 | G23: https://store.steampowered.com/app/914800/ | H23: https://vndb.org/v23634 | I23: 400135 | J23: FOUND | K23: 12500 | L23: 11837 | M23: 663 | N23: 0.94696 | O23: Very Positive | P23: FOUND | Q23: 高热度（>198） | R23: 全年龄 | S23: TRUE | T23: FALSE | U23: has_ero=false | W23: FALSE | Y23: FALSE | Z23: ORIGINAL_INTERSECTION | AA23: TRUE | AB23: v23634 | AC23: r69236 | AD23: complete | AE23: TRUE | AF23: -50% | AG23: FALSE | AH23: 46242.565
A24: 2205000 | B24: Talk To Me | C24: 43859 | D24: 2020-01 | E24: 2020 | F24: 78.29 | G24: https://store.steampowered.com/app/2205000/ | H24: https://vndb.org/v19449 | J24: NOT_FOUND | K24: 0 | L24: 0 | M24: 0 | O24: No user reviews | P24: FOUND | Q24: 低热度（≤198） | R24: 非全年龄 | S24: FALSE | T24: TRUE | U24: VNDB minage=17; has_ero=true; uncensored=true | V24: 17 | W24: TRUE | X24: TRUE | Y24: FALSE | Z24: VNDB_ONLY_COMPLETE_INCREMENT | AA24: FALSE | AB24: v19449 | AC24: r46391 | AD24: complete | AE24: TRUE | AG24: FALSE | AH24: 46242.565
A25: 1011190 | B25: SIMULACRA 2 | C25: 43860 | D25: 2020-01 | E25: 2020 | F25: 78.26 | G25: https://store.steampowered.com/app/1011190/ | H25: https://vndb.org/v57038 | I25: 56838 | J25: FOUND | K25: 1686 | L25: 1461 | M25: 225 | N25: 0.86654804 | O25: Very Positive | P25: FOUND | Q25: 高热度（>198） | R25: 全年龄 | S25: TRUE | T25: FALSE | U25: VNDB minage=12; has_ero=false | V25: 12 | W25: FALSE | Y25: FALSE | Z25: ORIGINAL_INTERSECTION | AA25: TRUE | AB25: v57038 | AC25: r137195 | AD25: complete | AE25: TRUE | AF25: $7.99 | AG25: FALSE | AH25: 46242.565
A26: 1087800 | B26: Arranged | C26: 43861 | D26: 2020-01 | E26: 2020 | F26: 78.23 | G26: https://store.steampowered.com/app/1087800/ | H26: https://vndb.org/v27834 | I26: 522 | J26: FOUND | K26: 17 | L26: 14 | M26: 3 | N26: 0.82352941 | O26: Positive | P26: FOUND | Q26: 低热度（≤198） | R26: 全年龄 | S26: TRUE | T26: FALSE | U26: has_ero=false | W26: FALSE | Y26: FALSE | Z26: ORIGINAL_INTERSECTION | AA26: TRUE | AB26: v27834 | AC26: r69316 | AD26: complete | AE26: TRUE | AF26: $0.99 | AG26: FALSE | AH26: 46242.565
A27: 1106950 | B27: Furries & Scalies: Friendswood | C27: 43861 | D27: 2020-01 | E27: 2020 | F27: 78.23 | G27: https://store.steampowered.com/app/1106950/ | H27: https://vndb.org/v27836 | I27: 1 | J27: FOUND | K27: 1 | L27: 1 | M27: 0 | N27: 1 | O27: 1 user reviews | P27: FOUND | Q27: 低热度（≤198） | R27: 全年龄 | S27: TRUE | T27: FALSE | U27: has_ero=false | W27: FALSE | Y27: FALSE | Z27: ORIGINAL_INTERSECTION | AA27: TRUE | AB27: v27836 | AC27: r69318 | AD27: complete | AE27: TRUE | AF27: $9.99 | AG27: FALSE | AH27: 46242.565
A28: 942020 | B28: Grimm & Tonic: Aperitif | C28: 43861 | D28: 2020-01 | E28: 2020 | F28: 78.23 | G28: https://store.steampowered.com/app/942020/ | H28: https://vndb.org/v23383 | I28: 1170 | J28: FOUND | K28: 46 | L28: 28 | M28: 18 | N28: 0.60869565 | O28: Mixed | P28: FOUND | Q28: 低热度（≤198） | R28: 全年龄 | S28: TRUE | T28: FALSE | U28: VNDB minage=16; has_ero=false | V28: 16 | W28: FALSE | Y28: FALSE | Z28: ORIGINAL_INTERSECTION | AA28: TRUE | AB28: v23383 | AC28: r59581 | AD28: complete | AE28: TRUE | AF28: -75% | AG28: FALSE | AH28: 46242.565
A29: 1209330 | B29: Sakura Knight | C29: 43861 | D29: 2020-01 | E29: 2020 | F29: 78.23 | G29: https://store.steampowered.com/app/1209330/ | H29: https://vndb.org/v27835 | I29: 3973 | J29: FOUND | K29: 112 | L29: 92 | M29: 20 | N29: 0.82142857 | O29: Very Positive | P29: FOUND | Q29: 低热度（≤198） | R29: 全年龄 | S29: TRUE | T29: FALSE | U29: has_ero=false | W29: FALSE | Y29: FALSE | Z29: VNDB_ONLY_COMPLETE_INCREMENT | AA29: FALSE | AB29: v27835 | AC29: r69317 | AD29: complete | AE29: TRUE | AG29: FALSE | AH29: 46242.565
A30: 1139950 | B30: Two Weeks in Painland | C30: 43864 | D30: 2020-02 | E30: 2020 | F30: 78.13 | G30: https://store.steampowered.com/app/1139950/ | H30: https://vndb.org/v27946 | I30: 4690 | J30: FOUND | K30: 71 | L30: 61 | M30: 10 | N30: 0.85915493 | O30: Very Positive | P30: FOUND | Q30: 低热度（≤198） | R30: 全年龄 | S30: TRUE | T30: FALSE | U30: VNDB minage=16; has_ero=false | V30: 16 | W30: FALSE | Y30: FALSE | Z30: ORIGINAL_INTERSECTION | AA30: TRUE | AB30: v27946 | AC30: r69599 | AD30: complete | AE30: TRUE | AF30: Free | AG30: TRUE | AH30: 46242.565
A31: 1159660 | B31: Moe Era | C31: 43865 | D31: 2020-02 | E31: 2020 | F31: 78.09 | G31: https://store.steampowered.com/app/1159660/ | H31: https://vndb.org/v26814 | I31: 223698 | J31: FOUND | K31: 4818 | L31: 4215 | M31: 603 | N31: 0.87484433 | O31: Very Positive | P31: FOUND | Q31: 高热度（>198） | R31: 全年龄 | S31: TRUE | T31: FALSE | U31: has_ero=false | W31: FALSE | Y31: FALSE | Z31: ORIGINAL_INTERSECTION | AA31: TRUE | AB31: v26814 | AC31: r67090 | AD31: complete | AE31: TRUE | AF31: Free | AG31: TRUE | AH31: 46242.565
A32: 897220 | B32: Summer Pockets | C32: 43866 | D32: 2020-02 | E32: 2020 | F32: 78.06 | G32: https://store.steampowered.com/app/897220/ | H32: https://vndb.org/v20424 | I32: 99878 | J32: FOUND | K32: 4917 | L32: 4847 | M32: 70 | N32: 0.98576368 | O32: Overwhelmingly Positive | P32: FOUND | Q32: 高热度（>198） | R32: 全年龄 | S32: TRUE | T32: FALSE | U32: has_ero=false | W32: FALSE | Y32: FALSE | Z32: ORIGINAL_INTERSECTION | AA32: TRUE | AB32: v20424 | AC32: r71942 | AD32: complete | AE32: TRUE | AF32: $44.99 | AG32: FALSE | AH32: 46242.565
A33: 1207210 | B33: The foreigner | C33: 43866 | D33: 2020-02 | E33: 2020 | F33: 78.06 | G33: https://store.steampowered.com/app/1207210/ | H33: https://vndb.org/v27884 | I33: 1140 | J33: FOUND | K33: 32 | L33: 23 | M33: 9 | N33: 0.71875 | O33: Mostly Positive | P33: FOUND | Q33: 低热度（≤198） | R33: 全年龄 | S33: TRUE | T33: FALSE | U33: has_ero=false | W33: FALSE | Y33: FALSE | Z33: ORIGINAL_INTERSECTION | AA33: TRUE | AB33: v27884 | AC33: r87672 | AD33: complete | AE33: TRUE | AF33: $0.99 | AG33: FALSE | AH33: 46242.565
A34: 1174940 | B34: Kill or Love | C34: 43868 | D34: 2020-02 | E34: 2020 | F34: 78 | G34: https://store.steampowered.com/app/1174940/ | H34: https://vndb.org/v26356 | I34: 138834 | J34: FOUND | K34: 2183 | L34: 1946 | M34: 237 | N34: 0.89143381 | O34: Very Positive | P34: FOUND | Q34: 高热度（>198） | R34: 全年龄 | S34: TRUE | T34: FALSE | U34: VNDB minage=15; has_ero=false | V34: 15 | W34: FALSE | Y34: FALSE | Z34: ORIGINAL_INTERSECTION | AA34: TRUE | AB34: v26356 | AC34: r65534 | AD34: complete | AE34: TRUE | AF34: Free | AG34: TRUE | AH34: 46242.565
A35: 1224530 | B35: Naked News | C35: 43868 | D35: 2020-02 | E35: 2020 | F35: 78 | G35: https://store.steampowered.com/app/1224530/ | H35: https://vndb.org/v29089 | I35: 4879 | J35: FOUND | K35: 108 | L35: 70 | M35: 38 | N35: 0.64814815 | O35: Mixed | P35: FOUND | Q35: 低热度（≤198） | R35: 全年龄 | S35: TRUE | T35: FALSE | U35: has_ero=false | W35: FALSE | Y35: FALSE | Z35: ORIGINAL_INTERSECTION | AA35: TRUE | AB35: v29089 | AC35: r74121 | AD35: complete | AE35: TRUE | AF35: $0.99 | AG35: FALSE | AH35: 46242.565
A36: 1189440 | B36: VenusBlood FRONTIER International | C36: 43868 | D36: 2020-02 | E36: 2020 | F36: 78 | G36: https://store.steampowered.com/app/1189440/ | H36: https://vndb.org/v9409 | I36: 25607 | J36: FOUND | K36: 826 | L36: 774 | M36: 52 | N36: 0.937046 | O36: Very Positive | P36: FOUND | Q36: 高热度（>198） | R36: 全年龄 | S36: TRUE | T36: FALSE | U36: has_ero=false | W36: FALSE | Y36: FALSE | Z36: ORIGINAL_INTERSECTION | AA36: TRUE | AB36: v9409 | AC36: r84869 | AD36: complete | AE36: TRUE | AF36: $39.99 | AG36: FALSE | AH36: 46242.565
A37: 1209610 | B37: Virtually Real Life | C37: 43868 | D37: 2020-02 | E37: 2020 | F37: 78 | G37: https://store.steampowered.com/app/1209610/ | H37: https://vndb.org/v27979 | I37: 40 | J37: FOUND | K37: 3 | L37: 2 | M37: 1 | N37: 0.66666667 | O37: 3 user reviews | P37: FOUND | Q37: 低热度（≤198） | R37: 全年龄 | S37: TRUE | T37: FALSE | U37: VNDB minage=12; has_ero=false | V37: 12 | W37: FALSE | Y37: FALSE | Z37: ORIGINAL_INTERSECTION | AA37: TRUE | AB37: v27979 | AC37: r69684 | AD37: complete | AE37: TRUE | AF37: $3.99 | AG37: FALSE | AH37: 46242.565
A38: 1211650 | B38: Cirno's Perfect Summer Vacation | C38: 43871 | D38: 2020-02 | E38: 2020 | F38: 77.9 | G38: https://store.steampowered.com/app/1211650/ | H38: https://vndb.org/v26730 | I38: 8550 | J38: FOUND | K38: 95 | L38: 82 | M38: 13 | N38: 0.86315789 | O38: Very Positive | P38: FOUND | Q38: 低热度（≤198） | R38: 全年龄 | S38: TRUE | T38: FALSE | U38: VNDB minage=13; has_ero=false | V38: 13 | W38: FALSE | Y38: FALSE | Z38: ORIGINAL_INTERSECTION | AA38: TRUE | AB38: v26730 | AC38: r66855 | AD38: complete | AE38: TRUE | AF38: Free | AG38: TRUE | AH38: 46242.565
A39: 1232180 | B39: Sakuya Izayoi Gives You Advice And Dabs | C39: 43871 | D39: 2020-02 | E39: 2020 | F39: 77.9 | G39: https://store.steampowered.com/app/1232180/ | H39: https://vndb.org/v27913 | I39: 77050 | J39: FOUND | K39: 2412 | L39: 2351 | M39: 61 | N39: 0.97470978 | O39: Overwhelmingly Positive | P39: FOUND | Q39: 高热度（>198） | R39: 全年龄 | S39: TRUE | T39: FALSE | U39: has_ero=false | W39: FALSE | Y39: FALSE | Z39: ORIGINAL_INTERSECTION | AA39: TRUE | AB39: v27913 | AC39: r123940 | AD39: complete | AE39: TRUE | AF39: $0.99 | AG39: FALSE | AH39: 46242.565
A40: 812590 | B40: Awakening of Celestial | C40: 43873 | D40: 2020-02 | E40: 2020 | F40: 77.83 | G40: https://store.steampowered.com/app/812590/ | H40: https://vndb.org/v27929 | I40: 33 | J40: FOUND | K40: 5 | L40: 5 | M40: 0 | N40: 1 | O40: 5 user reviews | P40: FOUND | Q40: 低热度（≤198） | R40: 全年龄 | S40: TRUE | T40: FALSE | U40: has_ero=false | W40: FALSE | Y40: FALSE | Z40: ORIGINAL_INTERSECTION | AA40: TRUE | AB40: v27929 | AC40: r69544 | AD40: complete | AE40: TRUE | AF40: $9.99 | AG40: FALSE | AH40: 46242.565
A41: 1118910 | B41: Sunflower | C41: 43873 | D41: 2020-02 | E41: 2020 | F41: 77.83 | G41: https://store.steampowered.com/app/1118910/ | H41: https://vndb.org/v26172 | I41: 192 | J41: FOUND | K41: 11 | L41: 3 | M41: 8 | N41: 0.27272727 | O41: Mostly Negative | P41: FOUND | Q41: 低热度（≤198） | R41: 非全年龄 | S41: FALSE | T41: TRUE | U41: VNDB minage=18; has_ero=true; uncensored=true | V41: 18 | W41: TRUE | X41: TRUE | Y41: FALSE | Z41: VNDB_ONLY_COMPLETE_INCREMENT | AA41: FALSE | AB41: v26172 | AC41: r65038 | AD41: complete | AE41: TRUE | AG41: FALSE | AH41: 46242.565
A42: 1234030 | B42: ゴシックマーダー -運命を変えるアドベンチャー- | C42: 43873 | D42: 2020-02 | E42: 2020 | F42: 77.83 | G42: https://store.steampowered.com/app/1234030/ | H42: https://vndb.org/v27932 | I42: 1260 | J42: FOUND | K42: 33 | L42: 27 | M42: 6 | N42: 0.81818182 | O42: Positive | P42: FOUND | Q42: 低热度（≤198） | R42: 全年龄 | S42: TRUE | T42: FALSE | U42: has_ero=false | W42: FALSE | Y42: FALSE | Z42: ORIGINAL_INTERSECTION | AA42: TRUE | AB42: v27932 | AC42: r69550 | AD42: complete | AE42: TRUE | AF42: $11.99 | AG42: FALSE | AH42: 46242.565
A43: 1082700 | B43: Dinosaur Shakespeare: To Date or Not To Date? | C43: 43874 | D43: 2020-02 | E43: 2020 | F43: 77.8 | G43: https://store.steampowered.com/app/1082700/ | H43: https://vndb.org/v27939 | I43: 96 | J43: FOUND | K43: 4 | L43: 3 | M43: 1 | N43: 0.75 | O43: 4 user reviews | P43: FOUND | Q43: 低热度（≤198） | R43: 全年龄 | S43: TRUE | T43: FALSE | U43: has_ero=false | W43: FALSE | Y43: FALSE | Z43: ORIGINAL_INTERSECTION | AA43: TRUE | AB43: v27939 | AC43: r69569 | AD43: complete | AE43: TRUE | AF43: $9.99 | AG43: FALSE | AH43: 46242.565
A44: 1228960 | B44: Harolds Harem: The Neckoning | C44: 43874 | D44: 2020-02 | E44: 2020 | F44: 77.8 | G44: https://store.steampowered.com/app/1228960/ | H44: https://vndb.org/v30524 | I44: 328 | J44: FOUND | K44: 17 | L44: 17 | M44: 0 | N44: 1 | O44: Positive | P44: FOUND | Q44: 低热度（≤198） | R44: 全年龄 | S44: TRUE | T44: FALSE | U44: has_ero=false | W44: FALSE | Y44: FALSE | Z44: ORIGINAL_INTERSECTION | AA44: TRUE | AB44: v30524 | AC44: r78122 | AD44: complete | AE44: TRUE | AF44: $3.99 | AG44: FALSE | AH44: 46242.565
A45: 1171270 | B45: TroubleDays | C45: 43874 | D45: 2020-02 | E45: 2020 | F45: 77.8 | G45: https://store.steampowered.com/app/1171270/ | H45: https://vndb.org/v27751 | I45: 51089 | J45: FOUND | K45: 996 | L45: 904 | M45: 92 | N45: 0.90763052 | O45: Very Positive | P45: FOUND | Q45: 高热度（>198） | R45: 全年龄 | S45: TRUE | T45: FALSE | U45: has_ero=false | W45: FALSE | Y45: FALSE | Z45: VNDB_ONLY_COMPLETE_INCREMENT | AA45: FALSE | AB45: v27751 | AC45: r69108 | AD45: complete | AE45: TRUE | AG45: FALSE | AH45: 46242.565
A46: 1247700 | B46: Witch College 2 - 18+ Patch | C46: 43874 | D46: 2020-02 | E46: 2020 | F46: 77.8 | G46: https://store.steampowered.com/app/1247700/ | H46: https://vndb.org/v26858 | J46: NOT_FOUND | K46: 3 | L46: 2 | M46: 1 | N46: 0.66666667 | O46: 3 user reviews | P46: FOUND | Q46: 低热度（≤198） | R46: 非全年龄 | S46: FALSE | T46: TRUE | U46: VNDB minage=18; has_ero=true; uncensored=true | V46: 18 | W46: TRUE | X46: TRUE | Y46: FALSE | Z46: VNDB_ONLY_COMPLETE_INCREMENT | AA46: FALSE | AB46: v26858 | AC46: r69566 | AD46: complete | AE46: TRUE | AG46: FALSE | AH46: 46242.565
A47: 1220710 | B47: Ace In Space | C47: 43875 | D47: 2020-02 | E47: 2020 | F47: 77.77 | G47: https://store.steampowered.com/app/1220710/ | H47: https://vndb.org/v27943 | I47: 1329 | J47: FOUND | K47: 45 | L47: 40 | M47: 5 | N47: 0.88888889 | O47: Positive | P47: FOUND | Q47: 低热度（≤198） | R47: 全年龄 | S47: TRUE | T47: FALSE | U47: has_ero=false | W47: FALSE | Y47: FALSE | Z47: ORIGINAL_INTERSECTION | AA47: TRUE | AB47: v27943 | AC47: r69595 | AD47: complete | AE47: TRUE | AF47: $6.99 | AG47: FALSE | AH47: 46242.565
A48: 1041210 | B48: Mission: It's Complicated | C48: 43875 | D48: 2020-02 | E48: 2020 | F48: 77.77 | G48: https://store.steampowered.com/app/1041210/ | H48: https://vndb.org/v30535 | I48: 14245 | J48: FOUND | K48: 237 | L48: 219 | M48: 18 | N48: 0.92405063 | O48: Very Positive | P48: FOUND | Q48: 高热度（>198） | R48: 全年龄 | S48: TRUE | T48: FALSE | U48: has_ero=false | W48: FALSE | Y48: FALSE | Z48: ORIGINAL_INTERSECTION | AA48: TRUE | AB48: v30535 | AC48: r78173 | AD48: complete | AE48: TRUE | AF48: Free | AG48: TRUE | AH48: 46242.565
A49: 1218760 | B49: Moe Moe World War II-3 Deluxe Edition 萌萌２次大戰（略）３豪華限定版 | C49: 43875 | D49: 2020-02 | E49: 2020 | F49: 77.77 | G49: https://store.steampowered.com/app/1218760/ | H49: https://vndb.org/v23492 | I49: 118 | J49: FOUND | K49: 9 | L49: 8 | M49: 1 | N49: 0.88888889 | O49: 9 user reviews | P49: FOUND | Q49: 低热度（≤198） | R49: 全年龄 | S49: TRUE | T49: FALSE | U49: VNDB minage=0; has_ero=false | V49: 0 | W49: FALSE | Y49: FALSE | Z49: VNDB_ONLY_COMPLETE_INCREMENT | AA49: FALSE | AB49: v23492 | AC49: r69584 | AD49: complete | AE49: TRUE | AG49: FALSE | AH49: 46242.565
A50: 1221890 | B50: SCP: One More Life | C50: 43875 | D50: 2020-02 | E50: 2020 | F50: 77.77 | G50: https://store.steampowered.com/app/1221890/ | H50: https://vndb.org/v27944 | I50: 546 | J50: FOUND | K50: 17 | L50: 12 | M50: 5 | N50: 0.70588235 | O50: Mostly Positive | P50: FOUND | Q50: 低热度（≤198） | R50: 全年龄 | S50: TRUE | T50: FALSE | U50: has_ero=false | W50: FALSE | Y50: FALSE | Z50: ORIGINAL_INTERSECTION | AA50: TRUE | AB50: v27944 | AC50: r69596 | AD50: complete | AE50: TRUE | AF50: $3.99 | AG50: FALSE | AH50: 46242.565
A51: 1144400 | B51: Senren＊Banka | C51: 43875 | D51: 2020-02 | E51: 2020 | F51: 77.77 | G51: https://store.steampowered.com/app/1144400/ | H51: https://vndb.org/v19073 | I51: 1104424 | J51: FOUND | K51: 36670 | L51: 36116 | M51: 554 | N51: 0.98489228 | O51: Overwhelmingly Positive | P51: FOUND | Q51: 高热度（>198） | R51: 全年龄 | S51: TRUE | T51: FALSE | U51: has_ero=false | W51: FALSE | Y51: FALSE | Z51: ORIGINAL_INTERSECTION | AA51: TRUE | AB51: v19073 | AC51: r52360 | AD51: complete | AE51: TRUE | AF51: $34.99 | AG51: FALSE | AH51: 46242.565
A52: 1167790 | B52: 绝望监牢 / 絶望プリズン | C52: 43875 | D52: 2020-02 | E52: 2020 | F52: 77.77 | G52: https://store.steampowered.com/app/1167790/ | H52: https://vndb.org/v43332 | I52: 32497 | J52: FOUND | K52: 527 | L52: 390 | M52: 137 | N52: 0.74003795 | O52: Mostly Positive | P52: FOUND | Q52: 高热度（>198） | R52: 全年龄 | S52: TRUE | T52: FALSE | U52: VNDB minage=15; has_ero=false | V52: 15 | W52: FALSE | Y52: FALSE | Z52: VNDB_ONLY_COMPLETE_INCREMENT | AA52: FALSE | AB52: v43332 | AC52: r105074 | AD52: complete | AE52: TRUE | AG52: FALSE | AH52: 46242.565
A53: 1236480 | B53: King of Volleyball | C53: 43876 | D53: 2020-02 | E53: 2020 | F53: 77.73 | G53: https://store.steampowered.com/app/1236480/ | H53: https://vndb.org/v27833 | I53: 179 | J53: FOUND | K53: 12 | L53: 6 | M53: 6 | N53: 0.5 | O53: Mixed | P53: FOUND | Q53: 低热度（≤198） | R53: 非全年龄 | S53: FALSE | T53: TRUE | U53: VNDB minage=18; has_ero=true; uncensored=false | V53: 18 | W53: TRUE | X53: FALSE | Y53: FALSE | Z53: ORIGINAL_INTERSECTION | AA53: TRUE | AB53: v27833 | AC53: r69634 | AD53: complete | AE53: TRUE | AF53: $3.99 | AG53: FALSE | AH53: 46242.565
A54: 1202770 | B54: kirakira stars idol project AI | C54: 43877 | D54: 2020-02 | E54: 2020 | F54: 77.7 | G54: https://store.steampowered.com/app/1202770/ | H54: https://vndb.org/v27959 | I54: 2816 | J54: FOUND | K54: 82 | L54: 70 | M54: 12 | N54: 0.85365854 | O54: Very Positive | P54: FOUND | Q54: 低热度（≤198） | R54: 全年龄 | S54: TRUE | T54: FALSE | U54: has_ero=false | W54: FALSE | Y54: FALSE | Z54: ORIGINAL_INTERSECTION | AA54: TRUE | AB54: v27959 | AC54: r69635 | AD54: complete | AE54: TRUE | AF54: $12.99 | AG54: FALSE | AH54: 46242.565
A55: 1232120 | B55: Aether Field | C55: 43878 | D55: 2020-02 | E55: 2020 | F55: 77.67 | G55: https://store.steampowered.com/app/1232120/ | H55: https://vndb.org/v27970 | I55: 783 | J55: FOUND | K55: 22 | L55: 16 | M55: 6 | N55: 0.72727273 | O55: Mostly Positive | P55: FOUND | Q55: 低热度（≤198） | R55: 全年龄 | S55: TRUE | T55: FALSE | U55: has_ero=false | W55: FALSE | Y55: FALSE | Z55: ORIGINAL_INTERSECTION | AA55: TRUE | AB55: v27970 | AC55: r69648 | AD55: complete | AE55: TRUE | AF55: $3.99 | AG55: FALSE | AH55: 46242.565
A56: 1235950 | B56: Introvert | C56: 43878 | D56: 2020-02 | E56: 2020 | F56: 77.67 | G56: https://store.steampowered.com/app/1235950/ | H56: https://vndb.org/v27971 | I56: 195 | J56: FOUND | K56: 10 | L56: 6 | M56: 4 | N56: 0.6 | O56: Mixed | P56: FOUND | Q56: 低热度（≤198） | R56: 非全年龄 | S56: FALSE | T56: TRUE | U56: VNDB minage=18; has_ero=true; uncensored=false | V56: 18 | W56: TRUE | X56: FALSE | Y56: FALSE | Z56: VNDB_ONLY_COMPLETE_INCREMENT | AA56: FALSE | AB56: v27971 | AC56: r69649 | AD56: complete | AE56: TRUE | AG56: FALSE | AH56: 46242.565
A57: 974910 | B57: Magical Diary: Wolf Hall | C57: 43878 | D57: 2020-02 | E57: 2020 | F57: 77.67 | G57: https://store.steampowered.com/app/974910/ | H57: https://vndb.org/v24966 | I57: 8405 | J57: FOUND | K57: 216 | L57: 197 | M57: 19 | N57: 0.91203704 | O57: Very Positive | P57: FOUND | Q57: 高热度（>198） | R57: 全年龄 | S57: TRUE | T57: FALSE | U57: has_ero=false | W57: FALSE | Y57: FALSE | Z57: ORIGINAL_INTERSECTION | AA57: TRUE | AB57: v24966 | AC57: r61278 | AD57: complete | AE57: TRUE | AF57: $24.99 | AG57: FALSE | AH57: 46242.565
A58: 926340 | B58: Roman's Christmas / 罗曼圣诞探案集 | C58: 43880 | D58: 2020-02 | E58: 2020 | F58: 77.6 | G58: https://store.steampowered.com/app/926340/ | H58: https://vndb.org/v26897 | I58: 27549 | J58: FOUND | K58: 1500 | L58: 1439 | M58: 61 | N58: 0.95933333 | O58: Overwhelmingly Positive | P58: FOUND | Q58: 高热度（>198） | R58: 全年龄 | S58: TRUE | T58: FALSE | U58: has_ero=false | W58: FALSE | Y58: FALSE | Z58: ORIGINAL_INTERSECTION | AA58: TRUE | AB58: v26897 | AC58: r76436 | AD58: complete | AE58: TRUE | AF58: $10.99 | AG58: FALSE | AH58: 46242.565
A59: 1123510 | B59: Самозванец | C59: 43880 | D59: 2020-02 | E59: 2020 | F59: 77.6 | G59: https://store.steampowered.com/app/1123510/ | H59: https://vndb.org/v27976 | I59: 826 | J59: FOUND | K59: 25 | L59: 15 | M59: 10 | N59: 0.6 | O59: Mixed | P59: FOUND | Q59: 低热度（≤198） | R59: 全年龄 | S59: TRUE | T59: FALSE | U59: has_ero=false | W59: FALSE | Y59: FALSE | Z59: ORIGINAL_INTERSECTION | AA59: TRUE | AB59: v27976 | AC59: r69676 | AD59: complete | AE59: TRUE | AF59: $3.99 | AG59: FALSE | AH59: 46242.565
A60: 944050 | B60: Sixth Night | C60: 43881 | D60: 2020-02 | E60: 2020 | F60: 77.57 | G60: https://store.steampowered.com/app/944050/ | H60: https://vndb.org/v27975 | I60: 1313 | J60: FOUND | K60: 49 | L60: 46 | M60: 3 | N60: 0.93877551 | O60: Positive | P60: FOUND | Q60: 低热度（≤198） | R60: 全年龄 | S60: TRUE | T60: FALSE | U60: has_ero=false | W60: FALSE | Y60: FALSE | Z60: VNDB_ONLY_COMPLETE_INCREMENT | AA60: FALSE | AB60: v27975 | AC60: r69675 | AD60: complete | AE60: TRUE | AG60: FALSE | AH60: 46242.565
A61: 1213550 | B61: Devil's Kiss | C61: 43882 | D61: 2020-02 | E61: 2020 | F61: 77.54 | G61: https://store.steampowered.com/app/1213550/ | H61: https://vndb.org/v27987 | I61: 2966 | J61: FOUND | K61: 106 | L61: 77 | M61: 29 | N61: 0.72641509 | O61: Mostly Positive | P61: FOUND | Q61: 低热度（≤198） | R61: 全年龄 | S61: TRUE | T61: FALSE | U61: has_ero=false | W61: FALSE | Y61: FALSE | Z61: ORIGINAL_INTERSECTION | AA61: TRUE | AB61: v27987 | AC61: r69731 | AD61: complete | AE61: TRUE | AF61: $1.99 | AG61: FALSE | AH61: 46242.565
A62: 1147760 | B62: The End of an Actress | C62: 43882 | D62: 2020-02 | E62: 2020 | F62: 77.54 | G62: https://store.steampowered.com/app/1147760/ | H62: https://vndb.org/v24666 | I62: 958 | J62: FOUND | K62: 35 | L62: 30 | M62: 5 | N62: 0.85714286 | O62: Positive | P62: FOUND | Q62: 低热度（≤198） | R62: 非全年龄 | S62: FALSE | T62: TRUE | U62: VNDB minage=18; has_ero=true; uncensored=true | V62: 18 | W62: TRUE | X62: TRUE | Y62: FALSE | Z62: ORIGINAL_INTERSECTION | AA62: TRUE | AB62: v24666 | AC62: r60564 | AD62: complete | AE62: TRUE | AF62: $9.99 | AG62: FALSE | AH62: 46242.565
A63: 973550 | B63: Yuuki's Party Night | C63: 43882 | D63: 2020-02 | E63: 2020 | F63: 77.54 | G63: https://store.steampowered.com/app/973550/ | H63: https://vndb.org/v27985 | I63: 662 | J63: FOUND | K63: 20 | L63: 13 | M63: 7 | N63: 0.65 | O63: Mixed | P63: FOUND | Q63: 低热度（≤198） | R63: 非全年龄 | S63: FALSE | T63: TRUE | U63: VNDB minage=18; has_ero=true; uncensored=true | V63: 18 | W63: TRUE | X63: TRUE | Y63: FALSE | Z63: VNDB_ONLY_COMPLETE_INCREMENT | AA63: FALSE | AB63: v27985 | AC63: r69725 | AD63: complete | AE63: TRUE | AG63: FALSE | AH63: 46242.565
A64: 1223810 | B64: Full Service | C64: 43883 | D64: 2020-02 | E64: 2020 | F64: 77.5 | G64: https://store.steampowered.com/app/1223810/ | H64: https://vndb.org/v20443 | I64: 15675 | J64: FOUND | K64: 555 | L64: 537 | M64: 18 | N64: 0.96756757 | O64: Overwhelmingly Positive | P64: FOUND | Q64: 高热度（>198） | R64: 非全年龄 | S64: FALSE | T64: TRUE | U64: VNDB minage=18; has_ero=true; uncensored=true | V64: 18 | W64: TRUE | X64: TRUE | Y64: FALSE | Z64: VNDB_ONLY_COMPLETE_INCREMENT | AA64: FALSE | AB64: v20443 | AC64: r49559 | AD64: complete | AE64: TRUE | AG64: FALSE | AH64: 46242.565
A65: 1730670 | B65: A Day in the Park | C65: 43884 | D65: 2020-02 | E65: 2020 | F65: 77.47 | G65: https://store.steampowered.com/app/1730670/ | H65: https://vndb.org/v27928 | I65: 200 | J65: FOUND | K65: 7 | L65: 6 | M65: 1 | N65: 0.85714286 | O65: 7 user reviews | P65: FOUND | Q65: 低热度（≤198） | R65: 非全年龄 | S65: FALSE | T65: TRUE | U65: VNDB minage=18; has_ero=true; uncensored=true | V65: 18 | W65: TRUE | X65: TRUE | Y65: FALSE | Z65: VNDB_ONLY_COMPLETE_INCREMENT | AA65: FALSE | AB65: v27928 | AC65: r83485 | AD65: complete | AE65: TRUE | AG65: FALSE | AH65: 46242.565
A66: 980430 | B66: HOT FIT! Complete version | C66: 43885 | D66: 2020-02 | E66: 2020 | F66: 77.44 | G66: https://store.steampowered.com/app/980430/ | H66: https://vndb.org/v20369 | J66: NOT_FOUND | K66: 0 | L66: 0 | M66: 0 | O66: No user reviews | P66: FOUND | Q66: 低热度（≤198） | R66: 非全年龄 | S66: FALSE | T66: TRUE | U66: VNDB minage=18; has_ero=true; uncensored=false | V66: 18 | W66: TRUE | X66: FALSE | Y66: FALSE | Z66: VNDB_ONLY_COMPLETE_INCREMENT | AA66: FALSE | AB66: v20369 | AC66: r69784 | AD66: complete | AE66: TRUE | AG66: FALSE | AH66: 46242.565
A67: 1244850 | B67: Witch College 2 | C67: 43885 | D67: 2020-02 | E67: 2020 | F67: 77.44 | G67: https://store.steampowered.com/app/1244850/ | H67: https://vndb.org/v26858 | I67: 288 | J67: FOUND | K67: 16 | L67: 10 | M67: 6 | N67: 0.625 | O67: Mixed | P67: FOUND | Q67: 低热度（≤198） | R67: 全年龄 | S67: TRUE | T67: FALSE | U67: has_ero=false | W67: FALSE | Y67: FALSE | Z67: ORIGINAL_INTERSECTION | AA67: TRUE | AB67: v26858 | AC67: r69565 | AD67: complete | AE67: TRUE | AF67: $4.99 | AG67: FALSE | AH67: 46242.565
A68: 1174400 | B68: Togainu no Chi ~Lost Blood~ | C68: 43886 | D68: 2020-02 | E68: 2020 | F68: 77.4 | G68: https://store.steampowered.com/app/1174400/ | H68: https://vndb.org/v434 | I68: 24894 | J68: FOUND | K68: 810 | L68: 784 | M68: 26 | N68: 0.96790123 | O68: Overwhelmingly Positive | P68: FOUND | Q68: 高热度（>198） | R68: 全年龄 | S68: TRUE | T68: FALSE | U68: VNDB minage=17; has_ero=false | V68: 17 | W68: FALSE | Y68: FALSE | Z68: ORIGINAL_INTERSECTION | AA68: TRUE | AB68: v434 | AC68: r69808;r69855 | AD68: complete;trial | AE68: TRUE | AF68: $19.99 | AG68: FALSE | AH68: 46242.565
A69: 1222060 | B69: 千里の棋譜 ～現代将棋ミステリー～ | C69: 43887 | D69: 2020-02 | E69: 2020 | F69: 77.37 | G69: https://store.steampowered.com/app/1222060/ | H69: https://vndb.org/v26903 | I69: 244 | J69: FOUND | K69: 13 | L69: 12 | M69: 1 | N69: 0.92307692 | O69: Positive | P69: FOUND | Q69: 低热度（≤198） | R69: 全年龄 | S69: TRUE | T69: FALSE | U69: has_ero=false | W69: FALSE | Y69: FALSE | Z69: ORIGINAL_INTERSECTION | AA69: TRUE | AB69: v26903 | AC69: r69070 | AD69: complete | AE69: TRUE | AF69: $29.99 | AG69: FALSE | AH69: 46242.565
A70: 1233270 | B70: OshiRabu: Waifus Over Husbandos | C70: 43888 | D70: 2020-02 | E70: 2020 | F70: 77.34 | G70: https://store.steampowered.com/app/1233270/ | H70: https://vndb.org/v27236 | I70: 74178 | J70: FOUND | K70: 3982 | L70: 3390 | M70: 592 | N70: 0.85133099 | O70: Very Positive | P70: FOUND | Q70: 高热度（>198） | R70: 全年龄 | S70: TRUE | T70: FALSE | U70: VNDB minage=0; has_ero=false | V70: 0 | W70: FALSE | Y70: FALSE | Z70: ORIGINAL_INTERSECTION | AA70: TRUE | AB70: v27236 | AC70: r69530 | AD70: complete | AE70: TRUE | AF70: $19.99 | AG70: FALSE | AH70: 46242.565
A71: 1189850 | B71: 鶴鄉戀旅 | C71: 43888 | D71: 2020-02 | E71: 2020 | F71: 77.34 | G71: https://store.steampowered.com/app/1189850/ | H71: https://vndb.org/v28039 | I71: 12593 | J71: FOUND | K71: 193 | L71: 190 | M71: 3 | N71: 0.98445596 | O71: Very Positive | P71: FOUND | Q71: 低热度（≤198） | R71: 全年龄 | S71: TRUE | T71: FALSE | U71: has_ero=false | W71: FALSE | Y71: FALSE | Z71: ORIGINAL_INTERSECTION | AA71: TRUE | AB71: v28039 | AC71: r69897 | AD71: complete | AE71: TRUE | AF71: Free | AG71: TRUE | AH71: 46242.565
A72: 1342290 | B72: Himeko Maid | C72: 43889 | D72: 2020-02 | E72: 2020 | F72: 77.31 | G72: https://store.steampowered.com/app/1342290/ | H72: https://vndb.org/v28087 | I72: 1027 | J72: FOUND | K72: 40 | L72: 37 | M72: 3 | N72: 0.925 | O72: Positive | P72: FOUND | Q72: 低热度（≤198） | R72: 非全年龄 | S72: FALSE | T72: TRUE | U72: VNDB minage=18; has_ero=true; uncensored=true | V72: 18 | W72: TRUE | X72: TRUE | Y72: FALSE | Z72: VNDB_ONLY_COMPLETE_INCREMENT | AA72: FALSE | AB72: v28087 | AC72: r70066 | AD72: complete | AE72: TRUE | AG72: FALSE | AH72: 46242.565
A73: 1202540 | B73: Marco & The Galaxy Dragon | C73: 43889 | D73: 2020-02 | E73: 2020 | F73: 77.31 | G73: https://store.steampowered.com/app/1202540/ | H73: https://vndb.org/v26902 | I73: 168357 | J73: FOUND | K73: 7821 | L73: 7611 | M73: 210 | N73: 0.97314921 | O73: Overwhelmingly Positive | P73: FOUND | Q73: 高热度（>198） | R73: 全年龄 | S73: TRUE | T73: FALSE | U73: VNDB minage=0; has_ero=false | V73: 0 | W73: FALSE | Y73: FALSE | Z73: ORIGINAL_INTERSECTION | AA73: TRUE | AB73: v26902 | AC73: r67327;r68634;r76628 | AD73: complete;trial | AE73: TRUE | AF73: $19.99 | AG73: FALSE | AH73: 46242.565
A74: 1212040 | B74: Paws & Effect: My Dogs Are Human! | C74: 43889 | D74: 2020-02 | E74: 2020 | F74: 77.31 | G74: https://store.steampowered.com/app/1212040/ | H74: https://vndb.org/v19258 | I74: 389 | J74: FOUND | K74: 16 | L74: 12 | M74: 4 | N74: 0.75 | O74: Mostly Positive | P74: FOUND | Q74: 低热度（≤198） | R74: 全年龄 | S74: TRUE | T74: FALSE | U74: VNDB minage=13; has_ero=false | V74: 13 | W74: FALSE | Y74: FALSE | Z74: ORIGINAL_INTERSECTION | AA74: TRUE | AB74: v19258 | AC74: r69901 | AD74: complete | AE74: TRUE | AF74: $4.99 | AG74: FALSE | AH74: 46242.565
A75: 1249850 | B75: King of Vikings | C75: 43890 | D75: 2020-02 | E75: 2020 | F75: 77.27 | G75: https://store.steampowered.com/app/1249850/ | H75: https://vndb.org/v27988 | I75: 267 | J75: FOUND | K75: 12 | L75: 8 | M75: 4 | N75: 0.66666667 | O75: Mixed | P75: FOUND | Q75: 低热度（≤198） | R75: 全年龄 | S75: TRUE | T75: FALSE | U75: VNDB minage=18; has_ero=false | V75: 18 | W75: FALSE | Y75: FALSE | Z75: ORIGINAL_INTERSECTION | AA75: TRUE | AB75: v27988 | AC75: r69736 | AD75: complete | AE75: TRUE | AF75: $3.99 | AG75: FALSE | AH75: 46242.565
A76: 1292440 | B76: Night and Day | C76: 43892 | D76: 2020-03 | E76: 2020 | F76: 77.21 | G76: https://store.steampowered.com/app/1292440/ | H76: https://vndb.org/v29707 | I76: 440 | J76: FOUND | K76: 22 | L76: 11 | M76: 11 | N76: 0.5 | O76: Mixed | P76: FOUND | Q76: 低热度（≤198） | R76: 非全年龄 | S76: FALSE | T76: TRUE | U76: VNDB minage=12/18; has_ero=false/true; uncensored=true | V76: 12;18 | W76: false;true | X76: TRUE | Y76: TRUE | Z76: VNDB_ONLY_COMPLETE_INCREMENT | AA76: FALSE | AB76: v29707 | AC76: r76009;r77110 | AD76: complete;trial | AE76: TRUE | AG76: FALSE | AH76: 46242.565
A77: 1156990 | B77: Return to Shironagasu Island | C77: 43892 | D77: 2020-03 | E77: 2020 | F77: 77.21 | G77: https://store.steampowered.com/app/1156990/ | H77: https://vndb.org/v25413 | I77: 141680 | J77: FOUND | K77: 4175 | L77: 3911 | M77: 264 | N77: 0.93676647 | O77: Very Positive | P77: FOUND | Q77: 高热度（>198） | R77: 全年龄 | S77: TRUE | T77: FALSE | U77: VNDB minage=15; has_ero=false | V77: 15 | W77: FALSE | Y77: FALSE | Z77: ORIGINAL_INTERSECTION | AA77: TRUE | AB77: v25413 | AC77: r124126;r95097 | AD77: complete | AE77: TRUE | AF77: $4.99 | AG77: FALSE | AH77: 46242.565
A78: 1236100 | B78: Of Evil and Darkness | C78: 43893 | D78: 2020-03 | E78: 2020 | F78: 77.17 | G78: https://store.steampowered.com/app/1236100/ | H78: https://vndb.org/v28051 | I78: 30 | J78: FOUND | K78: 2 | L78: 2 | M78: 0 | N78: 1 | O78: 2 user reviews | P78: FOUND | Q78: 低热度（≤198） | R78: 全年龄 | S78: TRUE | T78: FALSE | U78: has_ero=false | W78: FALSE | Y78: FALSE | Z78: ORIGINAL_INTERSECTION | AA78: TRUE | AB78: v28051 | AC78: r69935 | AD78: complete | AE78: TRUE | AF78: $1.99 | AG78: FALSE | AH78: 46242.565
A79: 1248870 | B79: イヌワシ ～うらぶれ探偵とお嬢様刑事の池袋事件ファイル～ | C79: 43893 | D79: 2020-03 | E79: 2020 | F79: 77.17 | G79: https://store.steampowered.com/app/1248870/ | H79: https://vndb.org/v28019 | I79: 336 | J79: FOUND | K79: 12 | L79: 9 | M79: 3 | N79: 0.75 | O79: Mostly Positive | P79: FOUND | Q79: 低热度（≤198） | R79: 全年龄 | S79: TRUE | T79: FALSE | U79: has_ero=false | W79: FALSE | Y79: FALSE | Z79: ORIGINAL_INTERSECTION | AA79: TRUE | AB79: v28019 | AC79: r69825 | AD79: complete | AE79: TRUE | AF79: $14.99 | AG79: FALSE | AH79: 46242.565
A80: 1123140 | B80: Mother Daughter Pleasure Pets | C80: 43895 | D80: 2020-03 | E80: 2020 | F80: 77.11 | G80: https://store.steampowered.com/app/1123140/ | H80: https://vndb.org/v19765 | I80: 5270 | J80: FOUND | K80: 122 | L80: 77 | M80: 45 | N80: 0.63114754 | O80: Mixed | P80: FOUND | Q80: 低热度（≤198） | R80: 非全年龄 | S80: FALSE | T80: TRUE | U80: VNDB minage=18; has_ero=true; uncensored=false | V80: 18 | W80: TRUE | X80: FALSE | Y80: FALSE | Z80: VNDB_ONLY_COMPLETE_INCREMENT | AA80: FALSE | AB80: v19765 | AC80: r123234 | AD80: complete | AE80: TRUE | AG80: FALSE | AH80: 46242.565
A81: 1140290 | B81: Murder by Numbers | C81: 43896 | D81: 2020-03 | E81: 2020 | F81: 77.08 | G81: https://store.steampowered.com/app/1140290/ | H81: https://vndb.org/v27484 | I81: 44477 | J81: FOUND | K81: 1680 | L81: 1412 | M81: 268 | N81: 0.84047619 | O81: Very Positive | P81: FOUND | Q81: 高热度（>198） | R81: 全年龄 | S81: TRUE | T81: FALSE | U81: has_ero=false | W81: FALSE | Y81: FALSE | Z81: ORIGINAL_INTERSECTION | AA81: TRUE | AB81: v27484 | AC81: r68539 | AD81: complete | AE81: TRUE | AF81: $14.99 | AG81: FALSE | AH81: 46242.565
A82: 1166110 | B82: Gods of Love: An Otome Visual Novel | C82: 43899 | D82: 2020-03 | E82: 2020 | F82: 76.98 | G82: https://store.steampowered.com/app/1166110/ | H82: https://vndb.org/v26870 | I82: 1716 | J82: FOUND | K82: 46 | L82: 32 | M82: 14 | N82: 0.69565217 | O82: Mixed | P82: FOUND | Q82: 低热度（≤198） | R82: 全年龄 | S82: TRUE | T82: FALSE | U82: VNDB minage=13; has_ero=false | V82: 13 | W82: FALSE | Y82: FALSE | Z82: ORIGINAL_INTERSECTION | AA82: TRUE | AB82: v26870 | AC82: r67232 | AD82: complete | AE82: TRUE | AF82: $15.99 | AG82: FALSE | AH82: 46242.565
A83: 1249980 | B83: 愛神餐館MAX | C83: 43899 | D83: 2020-03 | E83: 2020 | F83: 76.98 | G83: https://store.steampowered.com/app/1249980/ | H83: https://vndb.org/v21143 | I83: 1203 | J83: FOUND | K83: 53 | L83: 48 | M83: 5 | N83: 0.90566038 | O83: Very Positive | P83: FOUND | Q83: 低热度（≤198） | R83: 全年龄 | S83: TRUE | T83: FALSE | U83: has_ero=false | W83: FALSE | Y83: FALSE | Z83: VNDB_ONLY_COMPLETE_INCREMENT | AA83: FALSE | AB83: v21143 | AC83: r80697 | AD83: complete | AE83: TRUE | AG83: FALSE | AH83: 46242.565
A84: 1235400 | B84: CATharsis | C84: 43901 | D84: 2020-03 | E84: 2020 | F84: 76.91 | G84: https://store.steampowered.com/app/1235400/ | H84: https://vndb.org/v28099 | I84: 359 | J84: FOUND | K84: 14 | L84: 12 | M84: 2 | N84: 0.85714286 | O84: Positive | P84: FOUND | Q84: 低热度（≤198） | R84: 全年龄 | S84: TRUE | T84: FALSE | U84: has_ero=false | W84: FALSE | Y84: FALSE | Z84: ORIGINAL_INTERSECTION | AA84: TRUE | AB84: v28099 | AC84: r119521;r70120 | AD84: complete;trial | AE84: TRUE | AF84: $2.99 | AG84: FALSE | AH84: 46242.565
A85: 1161180 | B85: Funbag Fantasy: Sideboob Story 2 | C85: 43902 | D85: 2020-03 | E85: 2020 | F85: 76.88 | G85: https://store.steampowered.com/app/1161180/ | H85: https://vndb.org/v13083 | I85: 1088 | J85: FOUND | K85: 55 | L85: 54 | M85: 1 | N85: 0.98181818 | O85: Very Positive | P85: FOUND | Q85: 低热度（≤198） | R85: 非全年龄 | S85: FALSE | T85: TRUE | U85: VNDB minage=18; has_ero=true; uncensored=true | V85: 18 | W85: TRUE | X85: TRUE | Y85: FALSE | Z85: VNDB_ONLY_COMPLETE_INCREMENT | AA85: FALSE | AB85: v13083 | AC85: r64812 | AD85: complete | AE85: TRUE | AG85: FALSE | AH85: 46242.565
A86: 1217570 | B86: Lessons with Chii-chan | C86: 43902 | D86: 2020-03 | E86: 2020 | F86: 76.88 | G86: https://store.steampowered.com/app/1217570/ | H86: https://vndb.org/v19634 | I86: 7153 | J86: FOUND | K86: 179 | L86: 119 | M86: 60 | N86: 0.66480447 | O86: Mixed | P86: FOUND | Q86: 低热度（≤198） | R86: 全年龄 | S86: TRUE | T86: FALSE | U86: has_ero=false | W86: FALSE | Y86: FALSE | Z86: ORIGINAL_INTERSECTION | AA86: TRUE | AB86: v19634 | AC86: r123386 | AD86: complete | AE86: TRUE | AF86: $19.99 | AG86: FALSE | AH86: 46242.565
A87: 1207230 | B87: Seduce Me: The Complete Story | C87: 43904 | D87: 2020-03 | E87: 2020 | F87: 76.81 | G87: https://store.steampowered.com/app/1207230/ | H87: https://vndb.org/v14711 | I87: 1310 | J87: FOUND | K87: 52 | L87: 51 | M87: 1 | N87: 0.98076923 | O87: Very Positive | P87: FOUND | Q87: 低热度（≤198） | R87: 全年龄 | S87: TRUE | T87: FALSE | U87: has_ero=false | W87: FALSE | Y87: FALSE | Z87: VNDB_ONLY_COMPLETE_INCREMENT | AA87: FALSE | AB87: v14711;v16931;v17993;v19556;v19697;v19901;v20099;v20516;v21010;v22320;v22444;v22575;v24651;v27880 | AC87: r70001 | AD87: complete | AE87: TRUE | AG87: FALSE | AH87: 46242.565
A88: 1161870 | B88: Epiphyllum in Love | C88: 43906 | D88: 2020-03 | E88: 2020 | F88: 76.75 | G88: https://store.steampowered.com/app/1161870/ | H88: https://vndb.org/v28114 | I88: 40668 | J88: FOUND | K88: 2336 | L88: 2292 | M88: 44 | N88: 0.98116438 | O88: Overwhelmingly Positive | P88: FOUND | Q88: 高热度（>198） | R88: 全年龄 | S88: TRUE | T88: FALSE | U88: has_ero=false | W88: FALSE | Y88: FALSE | Z88: ORIGINAL_INTERSECTION | AA88: TRUE | AB88: v28114 | AC88: r86551 | AD88: complete | AE88: TRUE | AF88: $3.99 | AG88: FALSE | AH88: 46242.565
A89: 1238680 | B89: Amairo Chocolate | C89: 43909 | D89: 2020-03 | E89: 2020 | F89: 76.65 | G89: https://store.steampowered.com/app/1238680/ | H89: https://vndb.org/v26581 | I89: 25393 | J89: FOUND | K89: 1054 | L89: 1032 | M89: 22 | N89: 0.97912713 | O89: Overwhelmingly Positive | P89: FOUND | Q89: 高热度（>198） | R89: 全年龄 | S89: TRUE | T89: FALSE | U89: has_ero=false | W89: FALSE | Y89: FALSE | Z89: ORIGINAL_INTERSECTION | AA89: TRUE | AB89: v26581 | AC89: r70260 | AD89: complete | AE89: TRUE | AF89: $24.99 | AG89: FALSE | AH89: 46242.565
A90: 1246020 | B90: NOeSIS01_诉说谎言记忆物语 | C90: 43909 | D90: 2020-03 | E90: 2020 | F90: 76.65 | G90: https://store.steampowered.com/app/1246020/ | H90: https://vndb.org/v11029 | I90: 56768 | J90: FOUND | K90: 1535 | L90: 1502 | M90: 33 | N90: 0.97850163 | O90: Overwhelmingly Positive | P90: FOUND | Q90: 高热度（>198） | R90: 全年龄 | S90: TRUE | T90: FALSE | U90: VNDB minage=15; has_ero=false | V90: 15 | W90: FALSE | Y90: FALSE | Z90: ORIGINAL_INTERSECTION | AA90: TRUE | AB90: v11029 | AC90: r114297;r70000 | AD90: complete | AE90: TRUE | AF90: Free | AG90: TRUE | AH90: 46242.565
A91: 890700 | B91: Caffeine: Victoria's Legacy | C91: 43910 | D91: 2020-03 | E91: 2020 | F91: 76.62 | G91: https://store.steampowered.com/app/890700/ | H91: https://vndb.org/v24502 | I91: 816 | J91: FOUND | K91: 37 | L91: 34 | M91: 3 | N91: 0.91891892 | O91: Positive | P91: FOUND | Q91: 低热度（≤198） | R91: 全年龄 | S91: TRUE | T91: FALSE | U91: has_ero=false | W91: FALSE | Y91: FALSE | Z91: ORIGINAL_INTERSECTION | AA91: TRUE | AB91: v24502 | AC91: r60133 | AD91: complete | AE91: TRUE | AF91: $17.99 | AG91: FALSE | AH91: 46242.565
A92: 1048740 | B92: Half Past Fate | C92: 43910 | D92: 2020-03 | E92: 2020 | F92: 76.62 | G92: https://store.steampowered.com/app/1048740/ | H92: https://vndb.org/v51707 | I92: 6552 | J92: FOUND | K92: 303 | L92: 281 | M92: 22 | N92: 0.92739274 | O92: Very Positive | P92: FOUND | Q92: 高热度（>198） | R92: 全年龄 | S92: TRUE | T92: FALSE | U92: has_ero=false | W92: FALSE | Y92: FALSE | Z92: VNDB_ONLY_COMPLETE_INCREMENT | AA92: FALSE | AB92: v51707 | AC92: r125151 | AD92: complete | AE92: TRUE | AG92: FALSE | AH92: 46242.565
A93: 1201930 | B93: 末日临晓/The Dawn | C93: 43910 | D93: 2020-03 | E93: 2020 | F93: 76.62 | G93: https://store.steampowered.com/app/1201930/ | H93: https://vndb.org/v28132 | I93: 949 | J93: FOUND | K93: 30 | L93: 26 | M93: 4 | N93: 0.86666667 | O93: Positive | P93: FOUND | Q93: 低热度（≤198） | R93: 全年龄 | S93: TRUE | T93: FALSE | U93: VNDB minage=0; has_ero=false | V93: 0 | W93: FALSE | Y93: FALSE | Z93: VNDB_ONLY_COMPLETE_INCREMENT | AA93: FALSE | AB93: v28132 | AC93: r70287 | AD93: complete | AE93: TRUE | AG93: FALSE | AH93: 46242.565
A94: 1251680 | B94: Rescue Elves | C94: 43911 | D94: 2020-03 | E94: 2020 | F94: 76.58 | G94: https://store.steampowered.com/app/1251680/ | H94: https://vndb.org/v54706 | I94: 4043 | J94: FOUND | K94: 132 | L94: 84 | M94: 48 | N94: 0.63636364 | O94: Mixed | P94: FOUND | Q94: 低热度（≤198） | R94: 非全年龄 | S94: FALSE | T94: TRUE | U94: VNDB minage=18; has_ero=true; uncensored=true | V94: 18 | W94: TRUE | X94: TRUE | Y94: FALSE | Z94: VNDB_ONLY_COMPLETE_INCREMENT | AA94: FALSE | AB94: v54706 | AC94: r131797 | AD94: complete | AE94: TRUE | AG94: FALSE | AH94: 46242.565
A95: 1013820 | B95: Stars and Snowdrops | C95: 43912 | D95: 2020-03 | E95: 2020 | F95: 76.55 | G95: https://store.steampowered.com/app/1013820/ | H95: https://vndb.org/v28140 | I95: 850 | J95: FOUND | K95: 25 | L95: 21 | M95: 4 | N95: 0.84 | O95: Positive | P95: FOUND | Q95: 低热度（≤198） | R95: 全年龄 | S95: TRUE | T95: FALSE | U95: has_ero=false | W95: FALSE | Y95: FALSE | Z95: ORIGINAL_INTERSECTION | AA95: TRUE | AB95: v28140 | AC95: r70325 | AD95: complete | AE95: TRUE | AF95: $1.99 | AG95: FALSE | AH95: 46242.565
A96: 1264290 | B96: What's Inside?? | C96: 43913 | D96: 2020-03 | E96: 2020 | F96: 76.52 | G96: https://store.steampowered.com/app/1264290/ | H96: https://vndb.org/v28139 | I96: 1 | J96: FOUND | K96: 1 | L96: 1 | M96: 0 | N96: 1 | O96: 1 user reviews | P96: FOUND | Q96: 低热度（≤198） | R96: 全年龄 | S96: TRUE | T96: FALSE | U96: VNDB minage=0; has_ero=false | V96: 0 | W96: FALSE | Y96: FALSE | Z96: ORIGINAL_INTERSECTION | AA96: TRUE | AB96: v28139 | AC96: r70324 | AD96: complete | AE96: TRUE | AF96: $4.99 | AG96: FALSE | AH96: 46242.565
A97: 1162650 | B97: Ken ga Kimi | C97: 43915 | D97: 2020-03 | E97: 2020 | F97: 76.45 | G97: https://store.steampowered.com/app/1162650/ | H97: https://vndb.org/v11472 | I97: 26744 | J97: FOUND | K97: 1214 | L97: 1147 | M97: 67 | N97: 0.94481054 | O97: Very Positive | P97: FOUND | Q97: 高热度（>198） | R97: 全年龄 | S97: TRUE | T97: FALSE | U97: VNDB minage=15; has_ero=false | V97: 15 | W97: FALSE | Y97: FALSE | Z97: ORIGINAL_INTERSECTION | AA97: TRUE | AB97: v11472 | AC97: r67507 | AD97: complete | AE97: TRUE | AF97: $49.99 | AG97: FALSE | AH97: 46242.565
A98: 1258770 | B98: 6 PEOPLE | C98: 43916 | D98: 2020-03 | E98: 2020 | F98: 76.42 | G98: https://store.steampowered.com/app/1258770/ | H98: https://vndb.org/v28152 | I98: 4381 | J98: FOUND | K98: 59 | L98: 31 | M98: 28 | N98: 0.52542373 | O98: Mixed | P98: FOUND | Q98: 低热度（≤198） | R98: 全年龄 | S98: TRUE | T98: FALSE | U98: has_ero=false | W98: FALSE | Y98: FALSE | Z98: ORIGINAL_INTERSECTION | AA98: TRUE | AB98: v28152 | AC98: r70400 | AD98: complete | AE98: TRUE | AF98: Free | AG98: TRUE | AH98: 46242.565
A99: 1276610 | B99: My Cute Roommate | C99: 43916 | D99: 2020-03 | E99: 2020 | F99: 76.42 | G99: https://store.steampowered.com/app/1276610/ | H99: https://vndb.org/v31299 | I99: 26675 | J99: FOUND | K99: 688 | L99: 509 | M99: 179 | N99: 0.73982558 | O99: Mostly Positive | P99: FOUND | Q99: 高热度（>198） | R99: 非全年龄 | S99: FALSE | T99: TRUE | U99: VNDB minage=18; has_ero=true; uncensored=true | V99: 18 | W99: TRUE | X99: TRUE | Y99: FALSE | Z99: VNDB_ONLY_COMPLETE_INCREMENT | AA99: FALSE | AB99: v31299 | AC99: r80229 | AD99: complete | AE99: TRUE | AG99: FALSE | AH99: 46242.565
A100: 1258930 | B100: The Sunset that day, あの日見た夕陽 | C100: 43916 | D100: 2020-03 | E100: 2020 | F100: 76.42 | G100: https://store.steampowered.com/app/1258930/ | H100: https://vndb.org/v28153 | I100: 15 | J100: FOUND | K100: 1 | L100: 1 | M100: 0 | N100: 1 | O100: 1 user reviews | P100: FOUND | Q100: 低热度（≤198） | R100: 全年龄 | S100: TRUE | T100: FALSE | U100: has_ero=false | W100: FALSE | Y100: FALSE | Z100: ORIGINAL_INTERSECTION | AA100: TRUE | AB100: v28153 | AC100: r124037 | AD100: complete | AE100: TRUE | AF100: $6.99 | AG100: FALSE | AH100: 46242.565
...

Sheet 月度统计
A1: release_month | B1: game_count | C1: high_heat_count | D1: low_heat_count | E1: unknown_review_count | F1: all_ages_count | G1: not_all_ages_count | H1: unknown_age_count | I1: copies_sold_sum | J1: copies_sold_known
A2: 2020-01 | B2: 28 | C2: 8 | D2: 20 | E2: 0 | F2: 23 | G2: 5 | H2: 0 | I2: 835261 | J2: 26
A3: 2020-02 | B3: 46 | C3: 15 | D3: 31 | E3: 0 | F3: 36 | G3: 10 | H3: 0 | I3: 2135287 | J3: 44
A4: 2020-03 | B4: 31 | C4: 9 | D4: 22 | E4: 0 | F4: 24 | G4: 7 | H4: 0 | I4: 441906 | J4: 30
A5: 2020-04 | B5: 46 | C5: 14 | D5: 32 | E5: 0 | F5: 37 | G5: 9 | H5: 0 | I5: 379809 | J5: 39
A6: 2020-05 | B6: 37 | C6: 11 | D6: 26 | E6: 0 | F6: 29 | G6: 8 | H6: 0 | I6: 1349408 | J6: 30
A7: 2020-06 | B7: 44 | C7: 9 | D7: 35 | E7: 0 | F7: 40 | G7: 4 | H7: 0 | I7: 3513450 | J7: 42
A8: 2020-07 | B8: 50 | C8: 16 | D8: 34 | E8: 0 | F8: 41 | G8: 9 | H8: 0 | I8: 405896 | J8: 42
A9: 2020-08 | B9: 40 | C9: 12 | D9: 28 | E9: 0 | F9: 31 | G9: 9 | H9: 0 | I9: 1045748 | J9: 35
A10: 2020-09 | B10: 34 | C10: 8 | D10: 26 | E10: 0 | F10: 28 | G10: 6 | H10: 0 | I10: 302224 | J10: 32
A11: 2020-10 | B11: 53 | C11: 17 | D11: 36 | E11: 0 | F11: 44 | G11: 9 | H11: 0 | I11: 1005416 | J11: 46
A12: 2020-11 | B12: 44 | C12: 10 | D12: 34 | E12: 0 | F12: 39 | G12: 5 | H12: 0 | I12: 1462383 | J12: 36
A13: 2020-12 | B13: 45 | C13: 13 | D13: 32 | E13: 0 | F13: 33 | G13: 12 | H13: 0 | I13: 1132433 | J13: 41
... A73: 2025-12 | B73: 94 | C73: 9 | D73: 85 | E73: 0 | F73: 71 | G73: 23 | H73: 0 | I73: 789036 | J73: 83

Sheet 年度统计
A1: release_year | B1: game_count | C1: high_heat_count | D1: low_heat_count | E1: unknown_review_count | F1: all_ages_count | G1: not_all_ages_count | H1: unknown_age_count | I1: copies_sold_sum | J1: copies_sold_known
A2: 2020 | B2: 498 | C2: 142 | D2: 356 | E2: 0 | F2: 405 | G2: 93 | H2: 0 | I2: 14009221 | J2: 443
A3: 2021 | B3: 590 | C3: 152 | D3: 438 | E3: 0 | F3: 432 | G3: 158 | H3: 0 | I3: 14631664 | J3: 530
A4: 2022 | B4: 758 | C4: 143 | D4: 615 | E4: 0 | F4: 495 | G4: 263 | H4: 0 | I4: 11267193 | J4: 697
A5: 2023 | B5: 814 | C5: 143 | D5: 671 | E5: 0 | F5: 559 | G5: 255 | H5: 0 | I5: 12408258 | J5: 742
A6: 2024 | B6: 992 | C6: 192 | D6: 800 | E6: 0 | F6: 705 | G6: 287 | H6: 0 | I6: 10412483 | J6: 911
A7: 2025 | B7: 1008 | C7: 162 | D7: 846 | E7: 0 | F7: 740 | G7: 268 | H7: 0 | I7: 11701567 | J7: 936

Sheet 图表数据
A1: 月份 | B1: 全部游戏 | D1: 年份 | E1: 全部游戏 | G1: 月份 | H1: 高热度（>198） | I1: 低热度（≤198） | K1: 年份 | L1: 高热度（>198） | M1: 低热度（≤198） | O1: 月份 | P1: 全年龄 | Q1: 非全年龄 | R1: 未知 | T1: 年份 | U1: 全年龄 | V1: 非全年龄 | W1: 未知 | Y1: 上市月数 | Z1: 全部 log10销量 | AA1: 高热度（>198） log10销量 | AB1: 低热度（≤198） log10销量 | AC1: 全年龄 log10销量 | AD1: 非全年龄 log10销量 | AF1: 分类 | AG1: 游戏数
A2: =月度统计!A2 -> 2020-01 | B2: =月度统计!B2 -> 28 | D2: =年度统计!A2 -> 2020 | E2: =年度统计!B2 -> 498 | G2: =月度统计!A2 -> 2020-01 | H2: =月度统计!C2 -> 8 | I2: =月度统计!D2 -> 20 | K2: =年度统计!A2 -> 2020 | L2: =年度统计!C2 -> 142 | M2: =年度统计!D2 -> 356 | O2: =月度统计!A2 -> 2020-01 | P2: =月度统计!F2 -> 23 | Q2: =月度统计!G2 -> 5 | R2: =月度统计!H2 -> 0 | T2: =年度统计!A2 -> 2020 | U2: =年度统计!F2 -> 405 | V2: =年度统计!G2 -> 93 | W2: =年度统计!H2 -> 0 | Y2: =游戏总表!F2 -> 79.21 | Z2: =IF(游戏总表!I2>0,LOG(游戏总表!I2,10),"") -> 2.4424798 | AA2: =IF(AND(游戏总表!I2>0,游戏总表!Q2="高热度（>198）"),LOG(游戏总表!I2,10),"") | AB2: =IF(AND(游戏总表!I2>0,游戏总表!Q2="低热度（≤198）"),LOG(游戏总表!I2,10),"") -> 2.4424798 | AC2: =IF(AND(游戏总表!I2>0,游戏总表!R2="全年龄"),LOG(游戏总表!I2,10),"") -> 2.4424798 | AD2: =IF(AND(游戏总表!I2>0,游戏总表!R2="非全年龄"),LOG(游戏总表!I2,10),"") | AF2: 全年龄 | AG2: =COUNTIF(游戏总表!$R$2:$R$4661,AF2) -> 3336
A3: =月度统计!A3 -> 2020-02 | B3: =月度统计!B3 -> 46 | D3: =年度统计!A3 -> 2021 | E3: =年度统计!B3 -> 590 | G3: =月度统计!A3 -> 2020-02 | H3: =月度统计!C3 -> 15 | I3: =月度统计!D3 -> 31 | K3: =年度统计!A3 -> 2021 | L3: =年度统计!C3 -> 152 | M3: =年度统计!D3 -> 438 | O3: =月度统计!A3 -> 2020-02 | P3: =月度统计!F3 -> 36 | Q3: =月度统计!G3 -> 10 | R3: =月度统计!H3 -> 0 | T3: =年度统计!A3 -> 2021 | U3: =年度统计!F3 -> 432 | V3: =年度统计!G3 -> 158 | W3: =年度统计!H3 -> 0 | Y3: =游戏总表!F3 -> 79.18 | Z3: =IF(游戏总表!I3>0,LOG(游戏总表!I3,10),"") -> 4.4243752 | AA3: =IF(AND(游戏总表!I3>0,游戏总表!Q3="高热度（>198）"),LOG(游戏总表!I3,10),"") -> 4.4243752 | AB3: =IF(AND(游戏总表!I3>0,游戏总表!Q3="低热度（≤198）"),LOG(游戏总表!I3,10),"") | AC3: =IF(AND(游戏总表!I3>0,游戏总表!R3="全年龄"),LOG(游戏总表!I3,10),"") -> 4.4243752 | AD3: =IF(AND(游戏总表!I3>0,游戏总表!R3="非全年龄"),LOG(游戏总表!I3,10),"") | AF3: 非全年龄 | AG3: =COUNTIF(游戏总表!$R$2:$R$4661,AF3) -> 1324
A4: =月度统计!A4 -> 2020-03 | B4: =月度统计!B4 -> 31 | D4: =年度统计!A4 -> 2022 | E4: =年度统计!B4 -> 758 | G4: =月度统计!A4 -> 2020-03 | H4: =月度统计!C4 -> 9 | I4: =月度统计!D4 -> 22 | K4: =年度统计!A4 -> 2022 | L4: =年度统计!C4 -> 143 | M4: =年度统计!D4 -> 615 | O4: =月度统计!A4 -> 2020-03 | P4: =月度统计!F4 -> 24 | Q4: =月度统计!G4 -> 7 | R4: =月度统计!H4 -> 0 | T4: =年度统计!A4 -> 2022 | U4: =年度统计!F4 -> 495 | V4: =年度统计!G4 -> 263 | W4: =年度统计!H4 -> 0 | Y4: =游戏总表!F4 -> 79.18 | Z4: =IF(游戏总表!I4>0,LOG(游戏总表!I4,10),"") -> 4.9551969 | AA4: =IF(AND(游戏总表!I4>0,游戏总表!Q4="高热度（>198）"),LOG(游戏总表!I4,10),"") -> 4.9551969 | AB4: =IF(AND(游戏总表!I4>0,游戏总表!Q4="低热度（≤198）"),LOG(游戏总表!I4,10),"") | AC4: =IF(AND(游戏总表!I4>0,游戏总表!R4="全年龄"),LOG(游戏总表!I4,10),"") -> 4.9551969 | AD4: =IF(AND(游戏总表!I4>0,游戏总表!R4="非全年龄"),LOG(游戏总表!I4,10),"") | AF4: 未知 | AG4: =COUNTIF(游戏总表!$R$2:$R$4661,AF4) -> 0
A5: =月度统计!A5 -> 2020-04 | B5: =月度统计!B5 -> 46 | D5: =年度统计!A5 -> 2023 | E5: =年度统计!B5 -> 814 | G5: =月度统计!A5 -> 2020-04 | H5: =月度统计!C5 -> 14 | I5: =月度统计!D5 -> 32 | K5: =年度统计!A5 -> 2023 | L5: =年度统计!C5 -> 143 | M5: =年度统计!D5 -> 671 | O5: =月度统计!A5 -> 2020-04 | P5: =月度统计!F5 -> 37 | Q5: =月度统计!G5 -> 9 | R5: =月度统计!H5 -> 0 | T5: =年度统计!A5 -> 2023 | U5: =年度统计!F5 -> 559 | V5: =年度统计!G5 -> 255 | W5: =年度统计!H5 -> 0 | Y5: =游戏总表!F5 -> 79.15 | Z5: =IF(游戏总表!I5>0,LOG(游戏总表!I5,10),"") -> 2.071882 | AA5: =IF(AND(游戏总表!I5>0,游戏总表!Q5="高热度（>198）"),LOG(游戏总表!I5,10),"") | AB5: =IF(AND(游戏总表!I5>0,游戏总表!Q5="低热度（≤198）"),LOG(游戏总表!I5,10),"") -> 2.071882 | AC5: =IF(AND(游戏总表!I5>0,游戏总表!R5="全年龄"),LOG(游戏总表!I5,10),"") -> 2.071882 | AD5: =IF(AND(游戏总表!I5>0,游戏总表!R5="非全年龄"),LOG(游戏总表!I5,10),"")
A6: =月度统计!A6 -> 2020-05 | B6: =月度统计!B6 -> 37 | D6: =年度统计!A6 -> 2024 | E6: =年度统计!B6 -> 992 | G6: =月度统计!A6 -> 2020-05 | H6: =月度统计!C6 -> 11 | I6: =月度统计!D6 -> 26 | K6: =年度统计!A6 -> 2024 | L6: =年度统计!C6 -> 192 | M6: =年度统计!D6 -> 800 | O6: =月度统计!A6 -> 2020-05 | P6: =月度统计!F6 -> 29 | Q6: =月度统计!G6 -> 8 | R6: =月度统计!H6 -> 0 | T6: =年度统计!A6 -> 2024 | U6: =年度统计!F6 -> 705 | V6: =年度统计!G6 -> 287 | W6: =年度统计!H6 -> 0 | Y6: =游戏总表!F6 -> 78.92 | Z6: =IF(游戏总表!I6>0,LOG(游戏总表!I6,10),"") -> 2.146128 | AA6: =IF(AND(游戏总表!I6>0,游戏总表!Q6="高热度（>198）"),LOG(游戏总表!I6,10),"") | AB6: =IF(AND(游戏总表!I6>0,游戏总表!Q6="低热度（≤198）"),LOG(游戏总表!I6,10),"") -> 2.146128 | AC6: =IF(AND(游戏总表!I6>0,游戏总表!R6="全年龄"),LOG(游戏总表!I6,10),"") -> 2.146128 | AD6: =IF(AND(游戏总表!I6>0,游戏总表!R6="非全年龄"),LOG(游戏总表!I6,10),"")
A7: =月度统计!A7 -> 2020-06 | B7: =月度统计!B7 -> 44 | D7: =年度统计!A7 -> 2025 | E7: =年度统计!B7 -> 1008 | G7: =月度统计!A7 -> 2020-06 | H7: =月度统计!C7 -> 9 | I7: =月度统计!D7 -> 35 | K7: =年度统计!A7 -> 2025 | L7: =年度统计!C7 -> 162 | M7: =年度统计!D7 -> 846 | O7: =月度统计!A7 -> 2020-06 | P7: =月度统计!F7 -> 40 | Q7: =月度统计!G7 -> 4 | R7: =月度统计!H7 -> 0 | T7: =年度统计!A7 -> 2025 | U7: =年度统计!F7 -> 740 | V7: =年度统计!G7 -> 268 | W7: =年度统计!H7 -> 0 | Y7: =游戏总表!F7 -> 78.82 | Z7: =IF(游戏总表!I7>0,LOG(游戏总表!I7,10),"") -> 4.8835365 | AA7: =IF(AND(游戏总表!I7>0,游戏总表!Q7="高热度（>198）"),LOG(游戏总表!I7,10),"") -> 4.8835365 | AB7: =IF(AND(游戏总表!I7>0,游戏总表!Q7="低热度（≤198）"),LOG(游戏总表!I7,10),"") | AC7: =IF(AND(游戏总表!I7>0,游戏总表!R7="全年龄"),LOG(游戏总表!I7,10),"") -> 4.8835365 | AD7: =IF(AND(游戏总表!I7>0,游戏总表!R7="非全年龄"),LOG(游戏总表!I7,10),"")
A8: =月度统计!A8 -> 2020-07 | B8: =月度统计!B8 -> 50 | G8: =月度统计!A8 -> 2020-07 | H8: =月度统计!C8 -> 16 | I8: =月度统计!D8 -> 34 | O8: =月度统计!A8 -> 2020-07 | P8: =月度统计!F8 -> 41 | Q8: =月度统计!G8 -> 9 | R8: =月度统计!H8 -> 0 | Y8: =游戏总表!F8 -> 78.78 | Z8: =IF(游戏总表!I8>0,LOG(游戏总表!I8,10),"") -> 2.9786369 | AA8: =IF(AND(游戏总表!I8>0,游戏总表!Q8="高热度（>198）"),LOG(游戏总表!I8,10),"") | AB8: =IF(AND(游戏总表!I8>0,游戏总表!Q8="低热度（≤198）"),LOG(游戏总表!I8,10),"") -> 2.9786369 | AC8: =IF(AND(游戏总表!I8>0,游戏总表!R8="全年龄"),LOG(游戏总表!I8,10),"") -> 2.9786369 | AD8: =IF(AND(游戏总表!I8>0,游戏总表!R8="非全年龄"),LOG(游戏总表!I8,10),"")
A9: =月度统计!A9 -> 2020-08 | B9: =月度统计!B9 -> 40 | G9: =月度统计!A9 -> 2020-08 | H9: =月度统计!C9 -> 12 | I9: =月度统计!D9 -> 28 | O9: =月度统计!A9 -> 2020-08 | P9: =月度统计!F9 -> 31 | Q9: =月度统计!G9 -> 9 | R9: =月度统计!H9 -> 0 | Y9: =游戏总表!F9 -> 78.78 | Z9: =IF(游戏总表!I9>0,LOG(游戏总表!I9,10),"") -> 4.85083 | AA9: =IF(AND(游戏总表!I9>0,游戏总表!Q9="高热度（>198）"),LOG(游戏总表!I9,10),"") -> 4.85083 | AB9: =IF(AND(游戏总表!I9>0,游戏总表!Q9="低热度（≤198）"),LOG(游戏总表!I9,10),"") | AC9: =IF(AND(游戏总表!I9>0,游戏总表!R9="全年龄"),LOG(游戏总表!I9,10),"") -> 4.85083 | AD9: =IF(AND(游戏总表!I9>0,游戏总表!R9="非全年龄"),LOG(游戏总表!I9,10),"")
A10: =月度统计!A10 -> 2020-09 | B10: =月度统计!B10 -> 34 | G10: =月度统计!A10 -> 2020-09 | H10: =月度统计!C10 -> 8 | I10: =月度统计!D10 -> 26 | O10: =月度统计!A10 -> 2020-09 | P10: =月度统计!F10 -> 28 | Q10: =月度统计!G10 -> 6 | R10: =月度统计!H10 -> 0 | Y10: =游戏总表!F10 -> 78.72 | Z10: =IF(游戏总表!I10>0,LOG(游戏总表!I10,10),"") -> 4.0480143 | AA10: =IF(AND(游戏总表!I10>0,游戏总表!Q10="高热度（>198）"),LOG(游戏总表!I10,10),"") | AB10: =IF(AND(游戏总表!I10>0,游戏总表!Q10="低热度（≤198）"),LOG(游戏总表!I10,10),"") -> 4.0480143 | AC10: =IF(AND(游戏总表!I10>0,游戏总表!R10="全年龄"),LOG(游戏总表!I10,10),"") -> 4.0480143 | AD10: =IF(AND(游戏总表!I10>0,游戏总表!R10="非全年龄"),LOG(游戏总表!I10,10),"")
A11: =月度统计!A11 -> 2020-10 | B11: =月度统计!B11 -> 53 | G11: =月度统计!A11 -> 2020-10 | H11: =月度统计!C11 -> 17 | I11: =月度统计!D11 -> 36 | O11: =月度统计!A11 -> 2020-10 | P11: =月度统计!F11 -> 44 | Q11: =月度统计!G11 -> 9 | R11: =月度统计!H11 -> 0 | Y11: =游戏总表!F11 -> 78.69 | Z11: =IF(游戏总表!I11>0,LOG(游戏总表!I11,10),"") -> 2.5658478 | AA11: =IF(AND(游戏总表!I11>0,游戏总表!Q11="高热度（>198）"),LOG(游戏总表!I11,10),"") | AB11: =IF(AND(游戏总表!I11>0,游戏总表!Q11="低热度（≤198）"),LOG(游戏总表!I11,10),"") -> 2.5658478 | AC11: =IF(AND(游戏总表!I11>0,游戏总表!R11="全年龄"),LOG(游戏总表!I11,10),"") -> 2.5658478 | AD11: =IF(AND(游戏总表!I11>0,游戏总表!R11="非全年龄"),LOG(游戏总表!I11,10),"")
A12: =月度统计!A12 -> 2020-11 | B12: =月度统计!B12 -> 44 | G12: =月度统计!A12 -> 2020-11 | H12: =月度统计!C12 -> 10 | I12: =月度统计!D12 -> 34 | O12: =月度统计!A12 -> 2020-11 | P12: =月度统计!F12 -> 39 | Q12: =月度统计!G12 -> 5 | R12: =月度统计!H12 -> 0 | Y12: =游戏总表!F12 -> 78.69 | Z12: =IF(游戏总表!I12>0,LOG(游戏总表!I12,10),"") -> 3.1271048 | AA12: =IF(AND(游戏总表!I12>0,游戏总表!Q12="高热度（>198）"),LOG(游戏总表!I12,10),"") | AB12: =IF(AND(游戏总表!I12>0,游戏总表!Q12="低热度（≤198）"),LOG(游戏总表!I12,10),"") -> 3.1271048 | AC12: =IF(AND(游戏总表!I12>0,游戏总表!R12="全年龄"),LOG(游戏总表!I12,10),"") | AD12: =IF(AND(游戏总表!I12>0,游戏总表!R12="非全年龄"),LOG(游戏总表!I12,10),"") -> 3.1271048
A13: =月度统计!A13 -> 2020-12 | B13: =月度统计!B13 -> 45 | G13: =月度统计!A13 -> 2020-12 | H13: =月度统计!C13 -> 13 | I13: =月度统计!D13 -> 32 | O13: =月度统计!A13 -> 2020-12 | P13: =月度统计!F13 -> 33 | Q13: =月度统计!G13 -> 12 | R13: =月度统计!H13 -> 0 | Y13: =游戏总表!F13 -> 78.69 | Z13: =IF(游戏总表!I13>0,LOG(游戏总表!I13,10),"") -> 2.146128 | AA13: =IF(AND(游戏总表!I13>0,游戏总表!Q13="高热度（>198）"),LOG(游戏总表!I13,10),"") | AB13: =IF(AND(游戏总表!I13>0,游戏总表!Q13="低热度（≤198）"),LOG(游戏总表!I13,10),"") -> 2.146128 | AC13: =IF(AND(游戏总表!I13>0,游戏总表!R13="全年龄"),LOG(游戏总表!I13,10),"") -> 2.146128 | AD13: =IF(AND(游戏总表!I13>0,游戏总表!R13="非全年龄"),LOG(游戏总表!I13,10),"")
A14: =月度统计!A14 -> 2021-01 | B14: =月度统计!B14 -> 44 | G14: =月度统计!A14 -> 2021-01 | H14: =月度统计!C14 -> 13 | I14: =月度统计!D14 -> 31 | O14: =月度统计!A14 -> 2021-01 | P14: =月度统计!F14 -> 37 | Q14: =月度统计!G14 -> 7 | R14: =月度统计!H14 -> 0 | Y14: =游戏总表!F14 -> 78.69 | Z14: =IF(游戏总表!I14>0,LOG(游戏总表!I14,10),"") | AA14: =IF(AND(游戏总表!I14>0,游戏总表!Q14="高热度（>198）"),LOG(游戏总表!I14,10),"") | AB14: =IF(AND(游戏总表!I14>0,游戏总表!Q14="低热度（≤198）"),LOG(游戏总表!I14,10),"") | AC14: =IF(AND(游戏总表!I14>0,游戏总表!R14="全年龄"),LOG(游戏总表!I14,10),"") | AD14: =IF(AND(游戏总表!I14>0,游戏总表!R14="非全年龄"),LOG(游戏总表!I14,10),"")
A15: =月度统计!A15 -> 2021-02 | B15: =月度统计!B15 -> 42 | G15: =月度统计!A15 -> 2021-02 | H15: =月度统计!C15 -> 14 | I15: =月度统计!D15 -> 28 | O15: =月度统计!A15 -> 2021-02 | P15: =月度统计!F15 -> 31 | Q15: =月度统计!G15 -> 11 | R15: =月度统计!H15 -> 0 | Y15: =游戏总表!F15 -> 78.69 | Z15: =IF(游戏总表!I15>0,LOG(游戏总表!I15,10),"") -> 2.7143298 | AA15: =IF(AND(游戏总表!I15>0,游戏总表!Q15="高热度（>198）"),LOG(游戏总表!I15,10),"") | AB15: =IF(AND(游戏总表!I15>0,游戏总表!Q15="低热度（≤198）"),LOG(游戏总表!I15,10),"") -> 2.7143298 | AC15: =IF(AND(游戏总表!I15>0,游戏总表!R15="全年龄"),LOG(游戏总表!I15,10),"") -> 2.7143298 | AD15: =IF(AND(游戏总表!I15>0,游戏总表!R15="非全年龄"),LOG(游戏总表!I15,10),"")
A16: =月度统计!A16 -> 2021-03 | B16: =月度统计!B16 -> 39 | G16: =月度统计!A16 -> 2021-03 | H16: =月度统计!C16 -> 5 | I16: =月度统计!D16 -> 34 | O16: =月度统计!A16 -> 2021-03 | P16: =月度统计!F16 -> 26 | Q16: =月度统计!G16 -> 13 | R16: =月度统计!H16 -> 0 | Y16: =游戏总表!F16 -> 78.59 | Z16: =IF(游戏总表!I16>0,LOG(游戏总表!I16,10),"") -> 2.456366 | AA16: =IF(AND(游戏总表!I16>0,游戏总表!Q16="高热度（>198）"),LOG(游戏总表!I16,10),"") | AB16: =IF(AND(游戏总表!I16>0,游戏总表!Q16="低热度（≤198）"),LOG(游戏总表!I16,10),"") -> 2.456366 | AC16: =IF(AND(游戏总表!I16>0,游戏总表!R16="全年龄"),LOG(游戏总表!I16,10),"") -> 2.456366 | AD16: =IF(AND(游戏总表!I16>0,游戏总表!R16="非全年龄"),LOG(游戏总表!I16,10),"")
A17: =月度统计!A17 -> 2021-04 | B17: =月度统计!B17 -> 45 | G17: =月度统计!A17 -> 2021-04 | H17: =月度统计!C17 -> 14 | I17: =月度统计!D17 -> 31 | O17: =月度统计!A17 -> 2021-04 | P17: =月度统计!F17 -> 34 | Q17: =月度统计!G17 -> 11 | R17: =月度统计!H17 -> 0 | Y17: =游戏总表!F17 -> 78.59 | Z17: =IF(游戏总表!I17>0,LOG(游戏总表!I17,10),"") -> 2.2174839 | AA17: =IF(AND(游戏总表!I17>0,游戏总表!Q17="高热度（>198）"),LOG(游戏总表!I17,10),"") | AB17: =IF(AND(游戏总表!I17>0,游戏总表!Q17="低热度（≤198）"),LOG(游戏总表!I17,10),"") -> 2.2174839 | AC17: =IF(AND(游戏总表!I17>0,游戏总表!R17="全年龄"),LOG(游戏总表!I17,10),"") -> 2.2174839 | AD17: =IF(AND(游戏总表!I17>0,游戏总表!R17="非全年龄"),LOG(游戏总表!I17,10),"")
A18: =月度统计!A18 -> 2021-05 | B18: =月度统计!B18 -> 43 | G18: =月度统计!A18 -> 2021-05 | H18: =月度统计!C18 -> 12 | I18: =月度统计!D18 -> 31 | O18: =月度统计!A18 -> 2021-05 | P18: =月度统计!F18 -> 32 | Q18: =月度统计!G18 -> 11 | R18: =月度统计!H18 -> 0 | Y18: =游戏总表!F18 -> 78.49 | Z18: =IF(游戏总表!I18>0,LOG(游戏总表!I18,10),"") -> 4.7184934 | AA18: =IF(AND(游戏总表!I18>0,游戏总表!Q18="高热度（>198）"),LOG(游戏总表!I18,10),"") -> 4.7184934 | AB18: =IF(AND(游戏总表!I18>0,游戏总表!Q18="低热度（≤198）"),LOG(游戏总表!I18,10),"") | AC18: =IF(AND(游戏总表!I18>0,游戏总表!R18="全年龄"),LOG(游戏总表!I18,10),"") -> 4.7184934 | AD18: =IF(AND(游戏总表!I18>0,游戏总表!R18="非全年龄"),LOG(游戏总表!I18,10),"")
A19: =月度统计!A19 -> 2021-06 | B19: =月度统计!B19 -> 45 | G19: =月度统计!A19 -> 2021-06 | H19: =月度统计!C19 -> 13 | I19: =月度统计!D19 -> 32 | O19: =月度统计!A19 -> 2021-06 | P19: =月度统计!F19 -> 36 | Q19: =月度统计!G19 -> 9 | R19: =月度统计!H19 -> 0 | Y19: =游戏总表!F19 -> 78.49 | Z19: =IF(游戏总表!I19>0,LOG(游戏总表!I19,10),"") -> 4.5528142 | AA19: =IF(AND(游戏总表!I19>0,游戏总表!Q19="高热度（>198）"),LOG(游戏总表!I19,10),"") -> 4.5528142 | AB19: =IF(AND(游戏总表!I19>0,游戏总表!Q19="低热度（≤198）"),LOG(游戏总表!I19,10),"") | AC19: =IF(AND(游戏总表!I19>0,游戏总表!R19="全年龄"),LOG(游戏总表!I19,10),"") -> 4.5528142 | AD19: =IF(AND(游戏总表!I19>0,游戏总表!R19="非全年龄"),LOG(游戏总表!I19,10),"")
... A73: =月度统计!A73 -> 2025-12 | B73: =月度统计!B73 -> 94 | G73: =月度统计!A73 -> 2025-12 | H73: =月度统计!C73 -> 9 | I73: =月度统计!D73 -> 85 | O73: =月度统计!A73 -> 2025-12 | P73: =月度统计!F73 -> 71 | Q73: =月度统计!G73 -> 23 | R73: =月度统计!H73 -> 0 | Y73: =游戏总表!F73 -> 77.31 | Z73: =IF(游戏总表!I73>0,LOG(游戏总表!I73,10),"") -> 5.2262312 | AA73: =IF(AND(游戏总表!I73>0,游戏总表!Q73="高热度（>198）"),LOG(游戏总表!I73,10),"") -> 5.2262312 | AB73: =IF(AND(游戏总表!I73>0,游戏总表!Q73="低热度（≤198）"),LOG(游戏总表!I73,10),"") | AC73: =IF(AND(游戏总表!I73>0,游戏总表!R73="全年龄"),LOG(游戏总表!I73,10),"") -> 5.2262312 | AD73: =IF(AND(游戏总表!I73>0,游戏总表!R73="非全年龄"),LOG(游戏总表!I73,10),"")
Y74: =游戏总表!F74 -> 77.31 | Z74: =IF(游戏总表!I74>0,LOG(游戏总表!I74,10),"") -> 2.5899496 | AA74: =IF(AND(游戏总表!I74>0,游戏总表!Q74="高热度（>198）"),LOG(游戏总表!I74,10),"") | AB74: =IF(AND(游戏总表!I74>0,游戏总表!Q74="低热度（≤198）"),LOG(游戏总表!I74,10),"") -> 2.5899496 | AC74: =IF(AND(游戏总表!I74>0,游戏总表!R74="全年龄"),LOG(游戏总表!I74,10),"") -> 2.5899496 | AD74: =IF(AND(游戏总表!I74>0,游戏总表!R74="非全年龄"),LOG(游戏总表!I74,10),"")
Y75: =游戏总表!F75 -> 77.27 | Z75: =IF(游戏总表!I75>0,LOG(游戏总表!I75,10),"") -> 2.4265113 | AA75: =IF(AND(游戏总表!I75>0,游戏总表!Q75="高热度（>198）"),LOG(游戏总表!I75,10),"") | AB75: =IF(AND(游戏总表!I75>0,游戏总表!Q75="低热度（≤198）"),LOG(游戏总表!I75,10),"") -> 2.4265113 | AC75: =IF(AND(游戏总表!I75>0,游戏总表!R75="全年龄"),LOG(游戏总表!I75,10),"") -> 2.4265113 | AD75: =IF(AND(游戏总表!I75>0,游戏总表!R75="非全年龄"),LOG(游戏总表!I75,10),"")
Y76: =游戏总表!F76 -> 77.21 | Z76: =IF(游戏总表!I76>0,LOG(游戏总表!I76,10),"") -> 2.6434527 | AA76: =IF(AND(游戏总表!I76>0,游戏总表!Q76="高热度（>198）"),LOG(游戏总表!I76,10),"") | AB76: =IF(AND(游戏总表!I76>0,游戏总表!Q76="低热度（≤198）"),LOG(游戏总表!I76,10),"") -> 2.6434527 | AC76: =IF(AND(游戏总表!I76>0,游戏总表!R76="全年龄"),LOG(游戏总表!I76,10),"") | AD76: =IF(AND(游戏总表!I76>0,游戏总表!R76="非全年龄"),LOG(游戏总表!I76,10),"") -> 2.6434527
Y77: =游戏总表!F77 -> 77.21 | Z77: =IF(游戏总表!I77>0,LOG(游戏总表!I77,10),"") -> 5.1513085 | AA77: =IF(AND(游戏总表!I77>0,游戏总表!Q77="高热度（>198）"),LOG(游戏总表!I77,10),"") -> 5.1513085 | AB77: =IF(AND(游戏总表!I77>0,游戏总表!Q77="低热度（≤198）"),LOG(游戏总表!I77,10),"") | AC77: =IF(AND(游戏总表!I77>0,游戏总表!R77="全年龄"),LOG(游戏总表!I77,10),"") -> 5.1513085 | AD77: =IF(AND(游戏总表!I77>0,游戏总表!R77="非全年龄"),LOG(游戏总表!I77,10),"")
Y78: =游戏总表!F78 -> 77.17 | Z78: =IF(游戏总表!I78>0,LOG(游戏总表!I78,10),"") -> 1.4771213 | AA78: =IF(AND(游戏总表!I78>0,游戏总表!Q78="高热度（>198）"),LOG(游戏总表!I78,10),"") | AB78: =IF(AND(游戏总表!I78>0,游戏总表!Q78="低热度（≤198）"),LOG(游戏总表!I78,10),"") -> 1.4771213 | AC78: =IF(AND(游戏总表!I78>0,游戏总表!R78="全年龄"),LOG(游戏总表!I78,10),"") -> 1.4771213 | AD78: =IF(AND(游戏总表!I78>0,游戏总表!R78="非全年龄"),LOG(游戏总表!I78,10),"")
Y79: =游戏总表!F79 -> 77.17 | Z79: =IF(游戏总表!I79>0,LOG(游戏总表!I79,10),"") -> 2.5263393 | AA79: =IF(AND(游戏总表!I79>0,游戏总表!Q79="高热度（>198）"),LOG(游戏总表!I79,10),"") | AB79: =IF(AND(游戏总表!I79>0,游戏总表!Q79="低热度（≤198）"),LOG(游戏总表!I79,10),"") -> 2.5263393 | AC79: =IF(AND(游戏总表!I79>0,游戏总表!R79="全年龄"),LOG(游戏总表!I79,10),"") -> 2.5263393 | AD79: =IF(AND(游戏总表!I79>0,游戏总表!R79="非全年龄"),LOG(游戏总表!I79,10),"")
Y80: =游戏总表!F80 -> 77.11 | Z80: =IF(游戏总表!I80>0,LOG(游戏总表!I80,10),"") -> 3.7218106 | AA80: =IF(AND(游戏总表!I80>0,游戏总表!Q80="高热度（>198）"),LOG(游戏总表!I80,10),"") | AB80: =IF(AND(游戏总表!I80>0,游戏总表!Q80="低热度（≤198）"),LOG(游戏总表!I80,10),"") -> 3.7218106 | AC80: =IF(AND(游戏总表!I80>0,游戏总表!R80="全年龄"),LOG(游戏总表!I80,10),"") | AD80: =IF(AND(游戏总表!I80>0,游戏总表!R80="非全年龄"),LOG(游戏总表!I80,10),"") -> 3.7218106
Y81: =游戏总表!F81 -> 77.08 | Z81: =IF(游戏总表!I81>0,LOG(游戏总表!I81,10),"") -> 4.6481355 | AA81: =IF(AND(游戏总表!I81>0,游戏总表!Q81="高热度（>198）"),LOG(游戏总表!I81,10),"") -> 4.6481355 | AB81: =IF(AND(游戏总表!I81>0,游戏总表!Q81="低热度（≤198）"),LOG(游戏总表!I81,10),"") | AC81: =IF(AND(游戏总表!I81>0,游戏总表!R81="全年龄"),LOG(游戏总表!I81,10),"") -> 4.6481355 | AD81: =IF(AND(游戏总表!I81>0,游戏总表!R81="非全年龄"),LOG(游戏总表!I81,10),"")
Y82: =游戏总表!F82 -> 76.98 | Z82: =IF(游戏总表!I82>0,LOG(游戏总表!I82,10),"") -> 3.2345173 | AA82: =IF(AND(游戏总表!I82>0,游戏总表!Q82="高热度（>198）"),LOG(游戏总表!I82,10),"") | AB82: =IF(AND(游戏总表!I82>0,游戏总表!Q82="低热度（≤198）"),LOG(游戏总表!I82,10),"") -> 3.2345173 | AC82: =IF(AND(游戏总表!I82>0,游戏总表!R82="全年龄"),LOG(游戏总表!I82,10),"") -> 3.2345173 | AD82: =IF(AND(游戏总表!I82>0,游戏总表!R82="非全年龄"),LOG(游戏总表!I82,10),"")
Y83: =游戏总表!F83 -> 76.98 | Z83: =IF(游戏总表!I83>0,LOG(游戏总表!I83,10),"") -> 3.0802656 | AA83: =IF(AND(游戏总表!I83>0,游戏总表!Q83="高热度（>198）"),LOG(游戏总表!I83,10),"") | AB83: =IF(AND(游戏总表!I83>0,游戏总表!Q83="低热度（≤198）"),LOG(游戏总表!I83,10),"") -> 3.0802656 | AC83: =IF(AND(游戏总表!I83>0,游戏总表!R83="全年龄"),LOG(游戏总表!I83,10),"") -> 3.0802656 | AD83: =IF(AND(游戏总表!I83>0,游戏总表!R83="非全年龄"),LOG(游戏总表!I83,10),"")
Y84: =游戏总表!F84 -> 76.91 | Z84: =IF(游戏总表!I84>0,LOG(游戏总表!I84,10),"") -> 2.5550944 | AA84: =IF(AND(游戏总表!I84>0,游戏总表!Q84="高热度（>198）"),LOG(游戏总表!I84,10),"") | AB84: =IF(AND(游戏总表!I84>0,游戏总表!Q84="低热度（≤198）"),LOG(游戏总表!I84,10),"") -> 2.5550944 | AC84: =IF(AND(游戏总表!I84>0,游戏总表!R84="全年龄"),LOG(游戏总表!I84,10),"") -> 2.5550944 | AD84: =IF(AND(游戏总表!I84>0,游戏总表!R84="非全年龄"),LOG(游戏总表!I84,10),"")
Y85: =游戏总表!F85 -> 76.88 | Z85: =IF(游戏总表!I85>0,LOG(游戏总表!I85,10),"") -> 3.0366289 | AA85: =IF(AND(游戏总表!I85>0,游戏总表!Q85="高热度（>198）"),LOG(游戏总表!I85,10),"") | AB85: =IF(AND(游戏总表!I85>0,游戏总表!Q85="低热度（≤198）"),LOG(游戏总表!I85,10),"") -> 3.0366289 | AC85: =IF(AND(游戏总表!I85>0,游戏总表!R85="全年龄"),LOG(游戏总表!I85,10),"") | AD85: =IF(AND(游戏总表!I85>0,游戏总表!R85="非全年龄"),LOG(游戏总表!I85,10),"") -> 3.0366289
... Y4661: =游戏总表!F4661 -> 7.23 | Z4661: =IF(游戏总表!I4661>0,LOG(游戏总表!I4661,10),"") -> 2.3617278 | AA4661: =IF(AND(游戏总表!I4661>0,游戏总表!Q4661="高热度（>198）"),LOG(游戏总表!I4661,10),"") | AB4661: =IF(AND(游戏总表!I4661>0,游戏总表!Q4661="低热度（≤198）"),LOG(游戏总表!I4661,10),"") -> 2.3617278 | AC4661: =IF(AND(游戏总表!I4661>0,游戏总表!R4661="全年龄"),LOG(游戏总表!I4661,10),"") -> 2.3617278 | AD4661: =IF(AND(游戏总表!I4661>0,游戏总表!R4661="非全年龄"),LOG(游戏总表!I4661,10),"")

Sheet 图1_整体月度
A1: 2020–2025 视觉小说月度发行趋势（扩展口径） | S1: 月份 | T1: 全部游戏
S2: =月度统计!A2 -> 2020-01 | T2: =月度统计!B2 -> 28
S3: =月度统计!A3 -> 2020-02 | T3: =月度统计!B3 -> 46
S4: =月度统计!A4 -> 2020-03 | T4: =月度统计!B4 -> 31
S5: =月度统计!A5 -> 2020-04 | T5: =月度统计!B5 -> 46
S6: =月度统计!A6 -> 2020-05 | T6: =月度统计!B6 -> 37
S7: =月度统计!A7 -> 2020-06 | T7: =月度统计!B7 -> 44
S8: =月度统计!A8 -> 2020-07 | T8: =月度统计!B8 -> 50
S9: =月度统计!A9 -> 2020-08 | T9: =月度统计!B9 -> 40
S10: =月度统计!A10 -> 2020-09 | T10: =月度统计!B10 -> 34
S11: =月度统计!A11 -> 2020-10 | T11: =月度统计!B11 -> 53
S12: =月度统计!A12 -> 2020-11 | T12: =月度统计!B12 -> 44
S13: =月度统计!A13 -> 2020-12 | T13: =月度统计!B13 -> 45
... S24: =月度统计!A24 -> 2021-11 | T24: =月度统计!B24 -> 58
A25: 共 4,660 款；月份按 Steam 对应发行日归组。柱状与折线展示同一计数，便于同时观察规模和趋势。 | S25: =月度统计!A25 -> 2021-12 | T25: =月度统计!B25 -> 63
S26: =月度统计!A26 -> 2022-01 | T26: =月度统计!B26 -> 59
S27: =月度统计!A27 -> 2022-02 | T27: =月度统计!B27 -> 57
S28: =月度统计!A28 -> 2022-03 | T28: =月度统计!B28 -> 79
S29: =月度统计!A29 -> 2022-04 | T29: =月度统计!B29 -> 56
S30: =月度统计!A30 -> 2022-05 | T30: =月度统计!B30 -> 48
S31: =月度统计!A31 -> 2022-06 | T31: =月度统计!B31 -> 45
S32: =月度统计!A32 -> 2022-07 | T32: =月度统计!B32 -> 60
S33: =月度统计!A33 -> 2022-08 | T33: =月度统计!B33 -> 65
S34: =月度统计!A34 -> 2022-09 | T34: =月度统计!B34 -> 66
S35: =月度统计!A35 -> 2022-10 | T35: =月度统计!B35 -> 73
S36: =月度统计!A36 -> 2022-11 | T36: =月度统计!B36 -> 64
S37: =月度统计!A37 -> 2022-12 | T37: =月度统计!B37 -> 86
... S73: =月度统计!A73 -> 2025-12 | T73: =月度统计!B73 -> 94

Sheet 图2_整体年度
A1: 2020–2025 视觉小说年度发行趋势（扩展口径） | S1: 年份 | T1: 全部游戏
S2: =年度统计!A2 -> 2020 | T2: =年度统计!B2 -> 498
S3: =年度统计!A3 -> 2021 | T3: =年度统计!B3 -> 590
S4: =年度统计!A4 -> 2022 | T4: =年度统计!B4 -> 758
S5: =年度统计!A5 -> 2023 | T5: =年度统计!B5 -> 814
S6: =年度统计!A6 -> 2024 | T6: =年度统计!B6 -> 992
S7: =年度统计!A7 -> 2025 | T7: =年度统计!B7 -> 1008
A25: 年度汇总来自同一游戏总表；每个 Steam AppID 只计一次。

Sheet 图3_整体销量散点

Sheet 图4_热度月度
A1: 月度发行数量：评论数 >198 与 ≤198 | S1: 月份 | T1: 高热度（>198） | U1: 低热度（≤198）
S2: =月度统计!A2 -> 2020-01 | T2: =月度统计!C2 -> 8 | U2: =月度统计!D2 -> 20
S3: =月度统计!A3 -> 2020-02 | T3: =月度统计!C3 -> 15 | U3: =月度统计!D3 -> 31
S4: =月度统计!A4 -> 2020-03 | T4: =月度统计!C4 -> 9 | U4: =月度统计!D4 -> 22
S5: =月度统计!A5 -> 2020-04 | T5: =月度统计!C5 -> 14 | U5: =月度统计!D5 -> 32
S6: =月度统计!A6 -> 2020-05 | T6: =月度统计!C6 -> 11 | U6: =月度统计!D6 -> 26
S7: =月度统计!A7 -> 2020-06 | T7: =月度统计!C7 -> 9 | U7: =月度统计!D7 -> 35
S8: =月度统计!A8 -> 2020-07 | T8: =月度统计!C8 -> 16 | U8: =月度统计!D8 -> 34
S9: =月度统计!A9 -> 2020-08 | T9: =月度统计!C9 -> 12 | U9: =月度统计!D9 -> 28
S10: =月度统计!A10 -> 2020-09 | T10: =月度统计!C10 -> 8 | U10: =月度统计!D10 -> 26
S11: =月度统计!A11 -> 2020-10 | T11: =月度统计!C11 -> 17 | U11: =月度统计!D11 -> 36
S12: =月度统计!A12 -> 2020-11 | T12: =月度统计!C12 -> 10 | U12: =月度统计!D12 -> 34
S13: =月度统计!A13 -> 2020-12 | T13: =月度统计!C13 -> 13 | U13: =月度统计!D13 -> 32
... S24: =月度统计!A24 -> 2021-11 | T24: =月度统计!C24 -> 14 | U24: =月度统计!D24 -> 44
A25: 阈值 198 使评论数不超过阈值的游戏占 79.96%，约筛出热度最高的 20%。评论数来自 Steam 全语言、全部购买来源。 | S25: =月度统计!A25 -> 2021-12 | T25: =月度统计!C25 -> 15 | U25: =月度统计!D25 -> 48
S26: =月度统计!A26 -> 2022-01 | T26: =月度统计!C26 -> 12 | U26: =月度统计!D26 -> 47
S27: =月度统计!A27 -> 2022-02 | T27: =月度统计!C27 -> 11 | U27: =月度统计!D27 -> 46
S28: =月度统计!A28 -> 2022-03 | T28: =月度统计!C28 -> 19 | U28: =月度统计!D28 -> 60
S29: =月度统计!A29 -> 2022-04 | T29: =月度统计!C29 -> 12 | U29: =月度统计!D29 -> 44
S30: =月度统计!A30 -> 2022-05 | T30: =月度统计!C30 -> 8 | U30: =月度统计!D30 -> 40
S31: =月度统计!A31 -> 2022-06 | T31: =月度统计!C31 -> 8 | U31: =月度统计!D31 -> 37
S32: =月度统计!A32 -> 2022-07 | T32: =月度统计!C32 -> 14 | U32: =月度统计!D32 -> 46
S33: =月度统计!A33 -> 2022-08 | T33: =月度统计!C33 -> 16 | U33: =月度统计!D33 -> 49
S34: =月度统计!A34 -> 2022-09 | T34: =月度统计!C34 -> 13 | U34: =月度统计!D34 -> 53
S35: =月度统计!A35 -> 2022-10 | T35: =月度统计!C35 -> 15 | U35: =月度统计!D35 -> 58
S36: =月度统计!A36 -> 2022-11 | T36: =月度统计!C36 -> 6 | U36: =月度统计!D36 -> 58
S37: =月度统计!A37 -> 2022-12 | T37: =月度统计!C37 -> 9 | U37: =月度统计!D37 -> 77
... S73: =月度统计!A73 -> 2025-12 | T73: =月度统计!C73 -> 9 | U73: =月度统计!D73 -> 85

Sheet 图5_热度年度
A1: 年度发行数量：评论数 >198 与 ≤198 | S1: 年份 | T1: 高热度（>198） | U1: 低热度（≤198）
S2: =年度统计!A2 -> 2020 | T2: =年度统计!C2 -> 142 | U2: =年度统计!D2 -> 356
S3: =年度统计!A3 -> 2021 | T3: =年度统计!C3 -> 152 | U3: =年度统计!D3 -> 438
S4: =年度统计!A4 -> 2022 | T4: =年度统计!C4 -> 143 | U4: =年度统计!D4 -> 615
S5: =年度统计!A5 -> 2023 | T5: =年度统计!C5 -> 143 | U5: =年度统计!D5 -> 671
S6: =年度统计!A6 -> 2024 | T6: =年度统计!C6 -> 192 | U6: =年度统计!D6 -> 800
S7: =年度统计!A7 -> 2025 | T7: =年度统计!C7 -> 162 | U7: =年度统计!D7 -> 846
A25: 高热度：Steam 评论数 >198；低热度：Steam 评论数 ≤198。

Sheet 图6_热度销量散点

Sheet 图7_年龄月度
A1: 月度发行数量：全年龄与非全年龄（按 has_ero） | S1: 月份 | T1: 全年龄 | U1: 非全年龄
S2: =月度统计!A2 -> 2020-01 | T2: =月度统计!F2 -> 23 | U2: =月度统计!G2 -> 5
S3: =月度统计!A3 -> 2020-02 | T3: =月度统计!F3 -> 36 | U3: =月度统计!G3 -> 10
S4: =月度统计!A4 -> 2020-03 | T4: =月度统计!F4 -> 24 | U4: =月度统计!G4 -> 7
S5: =月度统计!A5 -> 2020-04 | T5: =月度统计!F5 -> 37 | U5: =月度统计!G5 -> 9
S6: =月度统计!A6 -> 2020-05 | T6: =月度统计!F6 -> 29 | U6: =月度统计!G6 -> 8
S7: =月度统计!A7 -> 2020-06 | T7: =月度统计!F7 -> 40 | U7: =月度统计!G7 -> 4
S8: =月度统计!A8 -> 2020-07 | T8: =月度统计!F8 -> 41 | U8: =月度统计!G8 -> 9
S9: =月度统计!A9 -> 2020-08 | T9: =月度统计!F9 -> 31 | U9: =月度统计!G9 -> 9
S10: =月度统计!A10 -> 2020-09 | T10: =月度统计!F10 -> 28 | U10: =月度统计!G10 -> 6
S11: =月度统计!A11 -> 2020-10 | T11: =月度统计!F11 -> 44 | U11: =月度统计!G11 -> 9
S12: =月度统计!A12 -> 2020-11 | T12: =月度统计!F12 -> 39 | U12: =月度统计!G12 -> 5
S13: =月度统计!A13 -> 2020-12 | T13: =月度统计!F13 -> 33 | U13: =月度统计!G13 -> 12
... S24: =月度统计!A24 -> 2021-11 | T24: =月度统计!F24 -> 42 | U24: =月度统计!G24 -> 16
A25: 任一关联 VNDB Release 的 has_ero=true 即归为非全年龄；否则已知 has_ero=false 归为全年龄。minage 不参与判断。 | S25: =月度统计!A25 -> 2021-12 | T25: =月度统计!F25 -> 44 | U25: =月度统计!G25 -> 19
S26: =月度统计!A26 -> 2022-01 | T26: =月度统计!F26 -> 44 | U26: =月度统计!G26 -> 15
S27: =月度统计!A27 -> 2022-02 | T27: =月度统计!F27 -> 40 | U27: =月度统计!G27 -> 17
S28: =月度统计!A28 -> 2022-03 | T28: =月度统计!F28 -> 49 | U28: =月度统计!G28 -> 30
S29: =月度统计!A29 -> 2022-04 | T29: =月度统计!F29 -> 26 | U29: =月度统计!G29 -> 30
S30: =月度统计!A30 -> 2022-05 | T30: =月度统计!F30 -> 31 | U30: =月度统计!G30 -> 17
S31: =月度统计!A31 -> 2022-06 | T31: =月度统计!F31 -> 28 | U31: =月度统计!G31 -> 17
S32: =月度统计!A32 -> 2022-07 | T32: =月度统计!F32 -> 43 | U32: =月度统计!G32 -> 17
S33: =月度统计!A33 -> 2022-08 | T33: =月度统计!F33 -> 50 | U33: =月度统计!G33 -> 15
S34: =月度统计!A34 -> 2022-09 | T34: =月度统计!F34 -> 40 | U34: =月度统计!G34 -> 26
S35: =月度统计!A35 -> 2022-10 | T35: =月度统计!F35 -> 51 | U35: =月度统计!G35 -> 22
S36: =月度统计!A36 -> 2022-11 | T36: =月度统计!F36 -> 42 | U36: =月度统计!G36 -> 22
S37: =月度统计!A37 -> 2022-12 | T37: =月度统计!F37 -> 51 | U37: =月度统计!G37 -> 35
... S73: =月度统计!A73 -> 2025-12 | T73: =月度统计!F73 -> 71 | U73: =月度统计!G73 -> 23

Sheet 图8_年龄年度
A1: 年度发行数量：全年龄与非全年龄（按 has_ero） | S1: 年份 | T1: 全年龄 | U1: 非全年龄
S2: =年度统计!A2 -> 2020 | T2: =年度统计!F2 -> 405 | U2: =年度统计!G2 -> 93
S3: =年度统计!A3 -> 2021 | T3: =年度统计!F3 -> 432 | U3: =年度统计!G3 -> 158
S4: =年度统计!A4 -> 2022 | T4: =年度统计!F4 -> 495 | U4: =年度统计!G4 -> 263
S5: =年度统计!A5 -> 2023 | T5: =年度统计!F5 -> 559 | U5: =年度统计!G5 -> 255
S6: =年度统计!A6 -> 2024 | T6: =年度统计!F6 -> 705 | U6: =年度统计!G6 -> 287
S7: =年度统计!A7 -> 2025 | T7: =年度统计!F7 -> 740 | U7: =年度统计!G7 -> 268
A25: 分类直接依据 VNDB Release.has_ero；本次样本没有 has_ero 未知项。

Sheet 图9_年龄销量散点

Sheet 图10_年龄占比
A1: 全年龄与非全年龄游戏占比（按 VNDB Release.has_ero） | S1: 分类 | T1: 游戏数
S2: 全年龄 | T2: =COUNTIF(游戏总表!$R$2:$R$4661,AF2) -> 0
S3: 非全年龄 | T3: =COUNTIF(游戏总表!$R$2:$R$4661,AF3) -> 0
S4: 未知 | T4: =COUNTIF(游戏总表!$R$2:$R$4661,AF4) -> 0
L5: 分类明细
L6: 分类 | M6: 游戏数 | N6: 占比
L7: 全年龄 | M7: =图表数据!AG2 -> 3336 | N7: =M7/SUM($M$7:$M$9) -> 0.71587983
L8: 非全年龄 | M8: =图表数据!AG3 -> 1324 | N8: =M8/SUM($M$7:$M$9) -> 0.28412017
L9: 未知 | M9: =图表数据!AG4 -> 0 | N9: =M9/SUM($M$7:$M$9) -> 0
A25: 非全年龄：任一关联 Release 的 has_ero=true；全年龄：无 true 且至少一个 has_ero=false。
